{
    "data": [
        {
            "id_posisi": "a03c1154-ad25-4ba8-ba6f-c9073826f62b",
            "posisi": "IT Networking Intern",
            "deskripsi_posisi": "1. Memberikan dukungan pada proyek instalasi dan looping kabel Fiber Optic (FO), termasuk penarikan, penyambungan, dan pengujian jaringan.\n2. Mendukung proyek instalasi dan pemasangan sistem CCTV, meliputi konfigurasi jaringan, integrasi perangkat, serta pengujian konektivitas.\n3. Melakukan troubleshooting dan maintenance jaringan, baik untuk perangkat aktif maupun pasif.\n4. Berkolaborasi dengan tim IT dan teknis lapangan untuk memastikan kelancaran implementasi proyek dan kualitas hasil instalasi.",
            "syarat_khusus": null,
            "usia_minimal": null,
            "usia_maksimal": null,
            "revisi": null,
            "id_kondisi_fisik": null,
            "id_program": "cc7136f4-90b2-45a2-ab20-029991da1743",
            "created_at": "2025-10-28 16:19:13",
            "updated_at": null,
            "kode_kbji": null,
            "penempatan": null,
            "id_jenis_kelamin": null,
            "id_status_posisi": 2,
            "jumlah_kuota": 1,
            "jumlah_terdaftar": 2,
            "program_studi": "[{\"id\":\"cbf82a7d-423a-4b1c-b3d7-c7c82d4cc46a\",\"title\":\"Teknik Komputer Dan Jaringan\"},{\"id\":\"d0101030-045d-42b0-8b74-574fe8ad6b5b\",\"title\":\"Teknologi Rekayasa Komputer Jaringan\"},{\"id\":\"03b570a2-c678-4413-aa47-bfed8308fac5\",\"title\":\"Teknik Informatika\"},{\"id\":\"8b6ace77-5ccd-4376-a5bd-73366799e9b6\",\"title\":\"Teknik Elektronika\"},{\"id\":\"4c7730b0-012a-401f-978f-98526dfca10b\",\"title\":\"Teknologi Rekayasa Elektronika\"}]",
            "jenjang": "[\"Diploma\",\"Sarjana\"]",
            "ref_status_posisi": {
                "id_status_posisi": 2,
                "nama_status_posisi": "Terverifikasi"
            },
            "program": {
                "id_program": "cc7136f4-90b2-45a2-ab20-029991da1743",
                "id_sumber_dana": null,
                "id_perusahaan": "7e765981-a049-4381-8051-1b89a7ad7f52",
                "id_jadwal": "48039861-1251-474e-86af-d904e829093b"
            },
            "perusahaan": {
                "id_perusahaan": "7e765981-a049-4381-8051-1b89a7ad7f52",
                "id_desa": null,
                "nama_perusahaan": "PT Makassar Metro Network",
                "deskripsi_perusahaan": "MMN toll road provides direct access from Makassar (largest city in eastern Indonesia) to harbour. The 10.25 km toll road connects Soekarno-Hatta port in Makassar and AP Pettarani road (Urip Sumoharjo flyover). The BMN toll road is also connected to the JTSE (Jalan Tol Seksi Empat) toll road midway. Its commercial operation started in 1998. JTSE toll road provides direct access from Makassar (largest city in eastern Indonesia) to airport. The 11.57 km toll road connects Tallo Bridge to the Mandai Makassar intersection, providing access to Sultan Hasanuddin International Airport as well as the national road to Maros. Its commercial operation started in 2008.",
                "alamat": "Gedung Menara Bosowa Lt. 4, Jl. Jenderal Sudirman No. 5, Makassar, Sulawesi Selatan - 90115",
                "logo": "https://wlkp-assets.kemnaker.go.id/companies/7e765981-a049-4381-8051-1b89a7ad7f52/60ca02a5952b4.png",
                "banner": "https://wlkp-assets.kemnaker.go.id/companies/7e765981-a049-4381-8051-1b89a7ad7f52/60ca02c99f99a.png",
                "created_at": "2025-10-28 16:19:13",
                "updated_at": null,
                "kode_kabupaten": "7371",
                "nama_kabupaten": "KOTA MAKASSAR",
                "kode_provinsi": "73",
                "nama_provinsi": "SULAWESI SELATAN"
            },
            "jadwal": {
                "id_jadwal": "48039861-1251-474e-86af-d904e829093b",
                "angkatan": "2",
                "tanggal_batas_pendaftaran": "2025-10-03 00:00:00",
                "tanggal_mulai": "2025-11-24 00:00:00",
                "tanggal_selesai": "2026-05-23 23:59:59",
                "tahun": "2025",
                "tanggal_rencana_mulai": "2025-10-24 00:00:00",
                "tanggal_rencana_akhir": "2025-11-11 23:59:59",
                "tanggal_seleksi_mulai": "2025-11-12 00:00:00",
                "tanggal_seleksi_akhir": "2025-11-20 23:59:59",
                "tanggal_usulan_mulai": "2025-10-01 00:00:00",
                "tanggal_usulan_akhir": "2025-10-08 00:00:00",
                "tanggal_persetujuan_awal": "2025-10-05 00:00:00",
                "tanggal_persetujuan_akhir": "2025-10-06 00:00:00",
                "tanggal_pendaftaran_awal": "2025-11-06 00:00:00",
                "tanggal_pendaftaran_akhir": "2025-11-14 23:59:59",
                "tanggal_pengumuman_mulai": "2025-11-14 00:00:00",
                "tanggal_pengumuman_akhir": "2025-11-20 23:59:59",
                "tanggal_lulus_awal": "2024-11-01 00:00:00",
                "tanggal_lulus_akhir": "2025-10-31 00:00:00",
                "publish": 1
            },
            "government_agency": {
                "government_agency_name": null
            },
            "sub_government_agency": {
                "sub_government_agency_name": null
            }
        },
        {
            "id_posisi": "a03c117c-c117-453a-a673-932d1c4f5737",
            "posisi": "Staff Operasional",
            "deskripsi_posisi": "Mengelola alur kerja harian, memastikan cabang bisnis operasional sesuai standar perusahaan, serta melakukan koordinasi dengan departemen lain untuk mencapai tujuan bisnis",
            "syarat_khusus": null,
            "usia_minimal": null,
            "usia_maksimal": null,
            "revisi": null,
            "id_kondisi_fisik": null,
            "id_program": "8cbc7dfe-77da-49ef-b96b-b5e2b8df39a0",
            "created_at": "2025-10-26 15:14:27",
            "updated_at": "2025-10-31 08:33:41",
            "kode_kbji": null,
            "penempatan": null,
            "id_jenis_kelamin": null,
            "id_status_posisi": 2,
            "jumlah_kuota": 1,
            "jumlah_terdaftar": 0,
            "program_studi": "[{\"id\":\"2fcca542-3387-47da-8b07-96e36b8225dc\",\"title\":\"Tata Boga\"},{\"id\":\"66985b26-ecaf-45a0-87c3-493c58823758\",\"title\":\"Pendidikan Tata Boga\"},{\"id\":\"e3668d6d-acab-4f65-8d20-262e73fe8f36\",\"title\":\"Manajemen Pemasaran\"},{\"id\":\"d3f1aee5-eb97-4b07-9029-557e1b03626b\",\"title\":\"Manajemen Pemasaran Pariwisata\"}]",
            "jenjang": "[\"Diploma\",\"Sarjana\"]",
            "ref_status_posisi": {
                "id_status_posisi": 2,
                "nama_status_posisi": "Terverifikasi"
            },
            "program": {
                "id_program": "8cbc7dfe-77da-49ef-b96b-b5e2b8df39a0",
                "id_sumber_dana": null,
                "id_perusahaan": "043d7efb-c78c-46f5-ba10-02c2b76e8f84",
                "id_jadwal": "48039861-1251-474e-86af-d904e829093b"
            },
            "perusahaan": {
                "id_perusahaan": "043d7efb-c78c-46f5-ba10-02c2b76e8f84",
                "id_desa": null,
                "nama_perusahaan": "Abuba Steak Rc Bogor",
                "deskripsi_perusahaan": null,
                "alamat": "Jl. Achmad Sobana, Jl. Bangbarung Raya No.1, RT.02/RW.07, Bantarjati, Kec. Bogor Utara, Kota Bogor, Jawa Barat 16153",
                "logo": null,
                "banner": null,
                "created_at": "2025-10-26 15:14:27",
                "updated_at": "2025-10-31 08:33:41",
                "kode_kabupaten": "3271",
                "nama_kabupaten": "KOTA BOGOR",
                "kode_provinsi": "32",
                "nama_provinsi": "JAWA BARAT"
            },
            "jadwal": {
                "id_jadwal": "48039861-1251-474e-86af-d904e829093b",
                "angkatan": "2",
                "tanggal_batas_pendaftaran": "2025-10-03 00:00:00",
                "tanggal_mulai": "2025-11-24 00:00:00",
                "tanggal_selesai": "2026-05-23 23:59:59",
                "tahun": "2025",
                "tanggal_rencana_mulai": "2025-10-24 00:00:00",
                "tanggal_rencana_akhir": "2025-11-11 23:59:59",
                "tanggal_seleksi_mulai": "2025-11-12 00:00:00",
                "tanggal_seleksi_akhir": "2025-11-20 23:59:59",
                "tanggal_usulan_mulai": "2025-10-01 00:00:00",
                "tanggal_usulan_akhir": "2025-10-08 00:00:00",
                "tanggal_persetujuan_awal": "2025-10-05 00:00:00",
                "tanggal_persetujuan_akhir": "2025-10-06 00:00:00",
                "tanggal_pendaftaran_awal": "2025-11-06 00:00:00",
                "tanggal_pendaftaran_akhir": "2025-11-14 23:59:59",
                "tanggal_pengumuman_mulai": "2025-11-14 00:00:00",
                "tanggal_pengumuman_akhir": "2025-11-20 23:59:59",
                "tanggal_lulus_awal": "2024-11-01 00:00:00",
                "tanggal_lulus_akhir": "2025-10-31 00:00:00",
                "publish": 1
            },
            "government_agency": {
                "government_agency_name": null
            },
            "sub_government_agency": {
                "sub_government_agency_name": null
            }
        },
        {
            "id_posisi": "a03c119f-4864-4251-9f49-87e7302624ae",
            "posisi": "ACCOUNTING",
            "deskripsi_posisi": "membantu penyusunan laporan keuangan, proses faktur, serta mendukung tim akuntansi dalam tugas-tugas harian seperti verifikasi dokumen keuangan",
            "syarat_khusus": null,
            "usia_minimal": null,
            "usia_maksimal": null,
            "revisi": null,
            "id_kondisi_fisik": null,
            "id_program": "239454a9-ce0e-42ed-81c1-8683a2cdb270",
            "created_at": "2025-10-30 09:14:53",
            "updated_at": null,
            "kode_kbji": null,
            "penempatan": null,
            "id_jenis_kelamin": null,
            "id_status_posisi": 2,
            "jumlah_kuota": 1,
            "jumlah_terdaftar": 1,
            "program_studi": "[{\"id\":\"c13ae920-a48f-4a7c-8c89-2b286a7fc225\",\"title\":\"Akuntansi\"},{\"id\":\"37972e05-4e53-4f9d-beb1-a301de6a2572\",\"title\":\"Akuntansi Keuangan\"},{\"id\":\"9fd1a1f4-4075-402d-a01a-2577ad024d1d\",\"title\":\"Manajemen Akuntansi Hospitaliti\"}]",
            "jenjang": "[\"Diploma\"]",
            "ref_status_posisi": {
                "id_status_posisi": 2,
                "nama_status_posisi": "Terverifikasi"
            },
            "program": {
                "id_program": "239454a9-ce0e-42ed-81c1-8683a2cdb270",
                "id_sumber_dana": null,
                "id_perusahaan": "f73e36e1-b7c0-4997-9035-762a40ef99a0",
                "id_jadwal": "48039861-1251-474e-86af-d904e829093b"
            },
            "perusahaan": {
                "id_perusahaan": "f73e36e1-b7c0-4997-9035-762a40ef99a0",
                "id_desa": null,
                "nama_perusahaan": "Mandiri Sukses Sejahtera",
                "deskripsi_perusahaan": null,
                "alamat": "Club House Permata Sidoarjo Regency, Jalan Raya Kludan, Tanggulangin Sidoarjo",
                "logo": null,
                "banner": null,
                "created_at": "2025-10-30 09:14:53",
                "updated_at": null,
                "kode_kabupaten": "3515",
                "nama_kabupaten": "KAB. SIDOARJO",
                "kode_provinsi": "35",
                "nama_provinsi": "JAWA TIMUR"
            },
            "jadwal": {
                "id_jadwal": "48039861-1251-474e-86af-d904e829093b",
                "angkatan": "2",
                "tanggal_batas_pendaftaran": "2025-10-03 00:00:00",
                "tanggal_mulai": "2025-11-24 00:00:00",
                "tanggal_selesai": "2026-05-23 23:59:59",
                "tahun": "2025",
                "tanggal_rencana_mulai": "2025-10-24 00:00:00",
                "tanggal_rencana_akhir": "2025-11-11 23:59:59",
                "tanggal_seleksi_mulai": "2025-11-12 00:00:00",
                "tanggal_seleksi_akhir": "2025-11-20 23:59:59",
                "tanggal_usulan_mulai": "2025-10-01 00:00:00",
                "tanggal_usulan_akhir": "2025-10-08 00:00:00",
                "tanggal_persetujuan_awal": "2025-10-05 00:00:00",
                "tanggal_persetujuan_akhir": "2025-10-06 00:00:00",
                "tanggal_pendaftaran_awal": "2025-11-06 00:00:00",
                "tanggal_pendaftaran_akhir": "2025-11-14 23:59:59",
                "tanggal_pengumuman_mulai": "2025-11-14 00:00:00",
                "tanggal_pengumuman_akhir": "2025-11-20 23:59:59",
                "tanggal_lulus_awal": "2024-11-01 00:00:00",
                "tanggal_lulus_akhir": "2025-10-31 00:00:00",
                "publish": 1
            },
            "government_agency": {
                "government_agency_name": null
            },
            "sub_government_agency": {
                "sub_government_agency_name": null
            }
        },
        {
            "id_posisi": "a03c122e-e28b-4e78-8805-0e5f9a834462",
            "posisi": "HR",
            "deskripsi_posisi": "dukungan administratif dalam rekrutmen, administrasi SDM, dan penggajian",
            "syarat_khusus": null,
            "usia_minimal": null,
            "usia_maksimal": null,
            "revisi": null,
            "id_kondisi_fisik": null,
            "id_program": "239454a9-ce0e-42ed-81c1-8683a2cdb270",
            "created_at": "2025-10-30 09:14:53",
            "updated_at": null,
            "kode_kbji": null,
            "penempatan": null,
            "id_jenis_kelamin": null,
            "id_status_posisi": 2,
            "jumlah_kuota": 1,
            "jumlah_terdaftar": 2,
            "program_studi": "[{\"id\":\"275bb92a-f5fa-485f-bf0c-5c0e9d4500d7\",\"title\":\"Manajemen Sumber Daya Manusia\"},{\"id\":\"3e1f167b-ac1f-4208-b1f7-ff2244791c64\",\"title\":\"Psikologi\"},{\"id\":\"fd3ebf70-4f4b-4dab-a7ab-ec31d20bd01b\",\"title\":\"Hukum\"}]",
            "jenjang": "[\"Sarjana\",\"Diploma\"]",
            "ref_status_posisi": {
                "id_status_posisi": 2,
                "nama_status_posisi": "Terverifikasi"
            },
            "program": {
                "id_program": "239454a9-ce0e-42ed-81c1-8683a2cdb270",
                "id_sumber_dana": null,
                "id_perusahaan": "f73e36e1-b7c0-4997-9035-762a40ef99a0",
                "id_jadwal": "48039861-1251-474e-86af-d904e829093b"
            },
            "perusahaan": {
                "id_perusahaan": "f73e36e1-b7c0-4997-9035-762a40ef99a0",
                "id_desa": null,
                "nama_perusahaan": "Mandiri Sukses Sejahtera",
                "deskripsi_perusahaan": null,
                "alamat": "Club House Permata Sidoarjo Regency, Jalan Raya Kludan, Tanggulangin Sidoarjo",
                "logo": null,
                "banner": null,
                "created_at": "2025-10-30 09:14:53",
                "updated_at": null,
                "kode_kabupaten": "3515",
                "nama_kabupaten": "KAB. SIDOARJO",
                "kode_provinsi": "35",
                "nama_provinsi": "JAWA TIMUR"
            },
            "jadwal": {
                "id_jadwal": "48039861-1251-474e-86af-d904e829093b",
                "angkatan": "2",
                "tanggal_batas_pendaftaran": "2025-10-03 00:00:00",
                "tanggal_mulai": "2025-11-24 00:00:00",
                "tanggal_selesai": "2026-05-23 23:59:59",
                "tahun": "2025",
                "tanggal_rencana_mulai": "2025-10-24 00:00:00",
                "tanggal_rencana_akhir": "2025-11-11 23:59:59",
                "tanggal_seleksi_mulai": "2025-11-12 00:00:00",
                "tanggal_seleksi_akhir": "2025-11-20 23:59:59",
                "tanggal_usulan_mulai": "2025-10-01 00:00:00",
                "tanggal_usulan_akhir": "2025-10-08 00:00:00",
                "tanggal_persetujuan_awal": "2025-10-05 00:00:00",
                "tanggal_persetujuan_akhir": "2025-10-06 00:00:00",
                "tanggal_pendaftaran_awal": "2025-11-06 00:00:00",
                "tanggal_pendaftaran_akhir": "2025-11-14 23:59:59",
                "tanggal_pengumuman_mulai": "2025-11-14 00:00:00",
                "tanggal_pengumuman_akhir": "2025-11-20 23:59:59",
                "tanggal_lulus_awal": "2024-11-01 00:00:00",
                "tanggal_lulus_akhir": "2025-10-31 00:00:00",
                "publish": 1
            },
            "government_agency": {
                "government_agency_name": null
            },
            "sub_government_agency": {
                "sub_government_agency_name": null
            }
        },
        {
            "id_posisi": "a03c124b-e417-46e6-b33d-c3363009a152",
            "posisi": "Mechanical Electrical & Rambu Keselamatan (Internship)",
            "deskripsi_posisi": "Industi: Toll Road\n\n1. Melaksanakan kegiatan pemeliharaan dan perawatan sistem jaringan listrik, termasuk instalasi dan panel distribusi.\n2. Membantu pemeliharaan Penerangan Jalan Umum (PJU) untuk memastikan fungsionalitas dan keselamatan pengguna jalan.\n3. Mendukung kegiatan pemeliharaan sistem mekanikal, mesin, serta peralatan kerja operasional.\n4. Berpartisipasi dalam pemeliharaan kendaraan operasional pemeliharaan dan rambu keselamatan jalan tol.\n5. Membantu tim dalam pencatatan, pelaporan, dan dokumentasi hasil kegiatan pemeliharaan sesuai Standar Operasional Prosedur (SOP) yang berlaku.",
            "syarat_khusus": null,
            "usia_minimal": null,
            "usia_maksimal": null,
            "revisi": null,
            "id_kondisi_fisik": null,
            "id_program": "cc7136f4-90b2-45a2-ab20-029991da1743",
            "created_at": "2025-10-28 16:19:13",
            "updated_at": null,
            "kode_kbji": null,
            "penempatan": null,
            "id_jenis_kelamin": null,
            "id_status_posisi": 2,
            "jumlah_kuota": 1,
            "jumlah_terdaftar": 3,
            "program_studi": "[{\"id\":\"93594dd7-0c1d-48c0-8f50-fd4bfde199b3\",\"title\":\"Teknik Elektro\"},{\"id\":\"8b6ace77-5ccd-4376-a5bd-73366799e9b6\",\"title\":\"Teknik Elektronika\"},{\"id\":\"02335732-9f44-4157-9e38-751b40ec3167\",\"title\":\"Instalasi dan Pemeliharaan Jaringan Listrik\"},{\"id\":\"21442969-5763-4416-bb8d-56a80e55ada9\",\"title\":\"Teknik Mesin\"},{\"id\":\"2be07689-5c0a-4a1c-8ce5-d9132f31c1b4\",\"title\":\"Pendidikan Vokasional Teknik Mesin\"}]",
            "jenjang": "[\"Diploma\",\"Sarjana\"]",
            "ref_status_posisi": {
                "id_status_posisi": 2,
                "nama_status_posisi": "Terverifikasi"
            },
            "program": {
                "id_program": "cc7136f4-90b2-45a2-ab20-029991da1743",
                "id_sumber_dana": null,
                "id_perusahaan": "7e765981-a049-4381-8051-1b89a7ad7f52",
                "id_jadwal": "48039861-1251-474e-86af-d904e829093b"
            },
            "perusahaan": {
                "id_perusahaan": "7e765981-a049-4381-8051-1b89a7ad7f52",
                "id_desa": null,
                "nama_perusahaan": "PT Makassar Metro Network",
                "deskripsi_perusahaan": "MMN toll road provides direct access from Makassar (largest city in eastern Indonesia) to harbour. The 10.25 km toll road connects Soekarno-Hatta port in Makassar and AP Pettarani road (Urip Sumoharjo flyover). The BMN toll road is also connected to the JTSE (Jalan Tol Seksi Empat) toll road midway. Its commercial operation started in 1998. JTSE toll road provides direct access from Makassar (largest city in eastern Indonesia) to airport. The 11.57 km toll road connects Tallo Bridge to the Mandai Makassar intersection, providing access to Sultan Hasanuddin International Airport as well as the national road to Maros. Its commercial operation started in 2008.",
                "alamat": "Gedung Menara Bosowa Lt. 4, Jl. Jenderal Sudirman No. 5, Makassar, Sulawesi Selatan - 90115",
                "logo": "https://wlkp-assets.kemnaker.go.id/companies/7e765981-a049-4381-8051-1b89a7ad7f52/60ca02a5952b4.png",
                "banner": "https://wlkp-assets.kemnaker.go.id/companies/7e765981-a049-4381-8051-1b89a7ad7f52/60ca02c99f99a.png",
                "created_at": "2025-10-28 16:19:13",
                "updated_at": null,
                "kode_kabupaten": "7371",
                "nama_kabupaten": "KOTA MAKASSAR",
                "kode_provinsi": "73",
                "nama_provinsi": "SULAWESI SELATAN"
            },
            "jadwal": {
                "id_jadwal": "48039861-1251-474e-86af-d904e829093b",
                "angkatan": "2",
                "tanggal_batas_pendaftaran": "2025-10-03 00:00:00",
                "tanggal_mulai": "2025-11-24 00:00:00",
                "tanggal_selesai": "2026-05-23 23:59:59",
                "tahun": "2025",
                "tanggal_rencana_mulai": "2025-10-24 00:00:00",
                "tanggal_rencana_akhir": "2025-11-11 23:59:59",
                "tanggal_seleksi_mulai": "2025-11-12 00:00:00",
                "tanggal_seleksi_akhir": "2025-11-20 23:59:59",
                "tanggal_usulan_mulai": "2025-10-01 00:00:00",
                "tanggal_usulan_akhir": "2025-10-08 00:00:00",
                "tanggal_persetujuan_awal": "2025-10-05 00:00:00",
                "tanggal_persetujuan_akhir": "2025-10-06 00:00:00",
                "tanggal_pendaftaran_awal": "2025-11-06 00:00:00",
                "tanggal_pendaftaran_akhir": "2025-11-14 23:59:59",
                "tanggal_pengumuman_mulai": "2025-11-14 00:00:00",
                "tanggal_pengumuman_akhir": "2025-11-20 23:59:59",
                "tanggal_lulus_awal": "2024-11-01 00:00:00",
                "tanggal_lulus_akhir": "2025-10-31 00:00:00",
                "publish": 1
            },
            "government_agency": {
                "government_agency_name": null
            },
            "sub_government_agency": {
                "sub_government_agency_name": null
            }
        },
        {
            "id_posisi": "a03c12ba-f52a-43cb-94cc-61ae1fb557a6",
            "posisi": "STAFF ADMIN PENJUALAN",
            "deskripsi_posisi": "Tugas & Tanggung Jawab Utama:\n1. Administrasi Pesanan Penjualan\n\nMenerima dan mencatat order dari pelanggan atau tim sales lapangan.\n\nMemastikan pesanan sesuai dengan harga, kuantitas, dan jadwal pengiriman.\n\nMembuat dan mencetak Surat Jalan, Faktur Penjualan, dan Nota Tagihan.\n\nBerkoordinasi dengan bagian Gudang & Produksi untuk ketersediaan stok.\n\n2. Pengelolaan Data & Dokumen Penjualan\n\nMengarsipkan dokumen pesanan, faktur, surat jalan, dan bukti penerimaan.\n\nMemasukkan data transaksi penjualan ke sistem (manual atau komputerisasi).\n\nMenjaga ketertiban dan akurasi data agar mudah ditelusuri saat audit.\n\n3. Penagihan & Pembayaran\n\nMembantu memantau status pembayaran pelanggan (piutang).\n\nMenginput dan mencocokkan data pembayaran dengan laporan keuangan.\n\nMembuat rekap tagihan mingguan/bulanan untuk diserahkan ke bagian Finance.\n\n4. Komunikasi & Koordinasi\n\nBerkoordinasi dengan tim sales lapangan, gudang, dan keuangan terkait pengiriman dan pembayaran.\n\nMemberikan informasi stok dan status pesanan kepada pelanggan atau sales.\n\nMenangani pertanyaan dan komplain administrasi pelanggan secara profesional.\n\n5. Pelaporan\n\nMembuat laporan penjualan harian, mingguan, dan bulanan kepada atasan.\n\nMenyusun rekap omset, retur, piutang, dan distribusi barang.\n\nMemberikan laporan akurat untuk evaluasi kinerja tim penjualan.\n\n6. Kegiatan Pendukung\n\nMembantu pelaksanaan promosi, event penjualan, dan program diskon.\n\nMenyiapkan dokumen untuk audit internal/eksternal.\n\nMenjaga kerahasiaan data pelanggan dan harga jual perusahaan.\n\n⚙️ Wewenang:\n\nMenginput, memvalidasi, dan mencetak dokumen penjualan resmi perusahaan.\n\nMenolak order yang tidak sesuai prosedur (tanpa PO atau limit kredit).\n\nMemberikan rekomendasi perbaikan sistem administrasi penjualan.",
            "syarat_khusus": null,
            "usia_minimal": null,
            "usia_maksimal": null,
            "revisi": null,
            "id_kondisi_fisik": null,
            "id_program": "9415ca3b-40af-4a2d-804d-11ba2526c381",
            "created_at": "2025-10-14 10:45:38",
            "updated_at": "2025-10-30 11:39:20",
            "kode_kbji": null,
            "penempatan": null,
            "id_jenis_kelamin": null,
            "id_status_posisi": 2,
            "jumlah_kuota": 1,
            "jumlah_terdaftar": 2,
            "program_studi": "[{\"id\":\"9d46d840-695e-4ecf-915c-ef58ebc36d9b\",\"title\":\"Administrasi Bisnis\"},{\"id\":\"fb8baadf-4b6f-423a-a499-07e330c61000\",\"title\":\"Administrasi Perkantoran\"}]",
            "jenjang": "[\"Sarjana\"]",
            "ref_status_posisi": {
                "id_status_posisi": 2,
                "nama_status_posisi": "Terverifikasi"
            },
            "program": {
                "id_program": "9415ca3b-40af-4a2d-804d-11ba2526c381",
                "id_sumber_dana": null,
                "id_perusahaan": "b13f02d0-293a-44bc-a95b-fbc314c8b515",
                "id_jadwal": "48039861-1251-474e-86af-d904e829093b"
            },
            "perusahaan": {
                "id_perusahaan": "b13f02d0-293a-44bc-a95b-fbc314c8b515",
                "id_desa": null,
                "nama_perusahaan": "Nata Bersaudara Sejahtera",
                "deskripsi_perusahaan": null,
                "alamat": "Jalan Mangkubumi Indihiang Blok Gunung Hanjuang",
                "logo": null,
                "banner": null,
                "created_at": "2025-10-14 10:45:38",
                "updated_at": "2025-10-30 11:39:20",
                "kode_kabupaten": "3278",
                "nama_kabupaten": "KOTA TASIKMALAYA",
                "kode_provinsi": "32",
                "nama_provinsi": "JAWA BARAT"
            },
            "jadwal": {
                "id_jadwal": "48039861-1251-474e-86af-d904e829093b",
                "angkatan": "2",
                "tanggal_batas_pendaftaran": "2025-10-03 00:00:00",
                "tanggal_mulai": "2025-11-24 00:00:00",
                "tanggal_selesai": "2026-05-23 23:59:59",
                "tahun": "2025",
                "tanggal_rencana_mulai": "2025-10-24 00:00:00",
                "tanggal_rencana_akhir": "2025-11-11 23:59:59",
                "tanggal_seleksi_mulai": "2025-11-12 00:00:00",
                "tanggal_seleksi_akhir": "2025-11-20 23:59:59",
                "tanggal_usulan_mulai": "2025-10-01 00:00:00",
                "tanggal_usulan_akhir": "2025-10-08 00:00:00",
                "tanggal_persetujuan_awal": "2025-10-05 00:00:00",
                "tanggal_persetujuan_akhir": "2025-10-06 00:00:00",
                "tanggal_pendaftaran_awal": "2025-11-06 00:00:00",
                "tanggal_pendaftaran_akhir": "2025-11-14 23:59:59",
                "tanggal_pengumuman_mulai": "2025-11-14 00:00:00",
                "tanggal_pengumuman_akhir": "2025-11-20 23:59:59",
                "tanggal_lulus_awal": "2024-11-01 00:00:00",
                "tanggal_lulus_akhir": "2025-10-31 00:00:00",
                "publish": 1
            },
            "government_agency": {
                "government_agency_name": null
            },
            "sub_government_agency": {
                "sub_government_agency_name": null
            }
        },
        {
            "id_posisi": "a03c145a-815b-4ab9-85d3-9c78641f649c",
            "posisi": "ARSITEK",
            "deskripsi_posisi": "membantu tim dalam proses desain, seperti membuat gambar dan model 3D, melakukan riset material dan referensi desain, serta menyiapkan presentasi",
            "syarat_khusus": null,
            "usia_minimal": null,
            "usia_maksimal": null,
            "revisi": null,
            "id_kondisi_fisik": null,
            "id_program": "239454a9-ce0e-42ed-81c1-8683a2cdb270",
            "created_at": "2025-10-30 09:14:53",
            "updated_at": null,
            "kode_kbji": null,
            "penempatan": null,
            "id_jenis_kelamin": null,
            "id_status_posisi": 2,
            "jumlah_kuota": 1,
            "jumlah_terdaftar": 2,
            "program_studi": "[{\"id\":\"4b75083a-8204-4373-a93f-f1ebb9c9778d\",\"title\":\"Arsitektur\"}]",
            "jenjang": "[\"Sarjana\"]",
            "ref_status_posisi": {
                "id_status_posisi": 2,
                "nama_status_posisi": "Terverifikasi"
            },
            "program": {
                "id_program": "239454a9-ce0e-42ed-81c1-8683a2cdb270",
                "id_sumber_dana": null,
                "id_perusahaan": "f73e36e1-b7c0-4997-9035-762a40ef99a0",
                "id_jadwal": "48039861-1251-474e-86af-d904e829093b"
            },
            "perusahaan": {
                "id_perusahaan": "f73e36e1-b7c0-4997-9035-762a40ef99a0",
                "id_desa": null,
                "nama_perusahaan": "Mandiri Sukses Sejahtera",
                "deskripsi_perusahaan": null,
                "alamat": "Club House Permata Sidoarjo Regency, Jalan Raya Kludan, Tanggulangin Sidoarjo",
                "logo": null,
                "banner": null,
                "created_at": "2025-10-30 09:14:53",
                "updated_at": null,
                "kode_kabupaten": "3515",
                "nama_kabupaten": "KAB. SIDOARJO",
                "kode_provinsi": "35",
                "nama_provinsi": "JAWA TIMUR"
            },
            "jadwal": {
                "id_jadwal": "48039861-1251-474e-86af-d904e829093b",
                "angkatan": "2",
                "tanggal_batas_pendaftaran": "2025-10-03 00:00:00",
                "tanggal_mulai": "2025-11-24 00:00:00",
                "tanggal_selesai": "2026-05-23 23:59:59",
                "tahun": "2025",
                "tanggal_rencana_mulai": "2025-10-24 00:00:00",
                "tanggal_rencana_akhir": "2025-11-11 23:59:59",
                "tanggal_seleksi_mulai": "2025-11-12 00:00:00",
                "tanggal_seleksi_akhir": "2025-11-20 23:59:59",
                "tanggal_usulan_mulai": "2025-10-01 00:00:00",
                "tanggal_usulan_akhir": "2025-10-08 00:00:00",
                "tanggal_persetujuan_awal": "2025-10-05 00:00:00",
                "tanggal_persetujuan_akhir": "2025-10-06 00:00:00",
                "tanggal_pendaftaran_awal": "2025-11-06 00:00:00",
                "tanggal_pendaftaran_akhir": "2025-11-14 23:59:59",
                "tanggal_pengumuman_mulai": "2025-11-14 00:00:00",
                "tanggal_pengumuman_akhir": "2025-11-20 23:59:59",
                "tanggal_lulus_awal": "2024-11-01 00:00:00",
                "tanggal_lulus_akhir": "2025-10-31 00:00:00",
                "publish": 1
            },
            "government_agency": {
                "government_agency_name": null
            },
            "sub_government_agency": {
                "sub_government_agency_name": null
            }
        },
        {
            "id_posisi": "a03c147e-8fc3-42bb-ac33-16e73f7a3da1",
            "posisi": "Admin Sales PCT",
            "deskripsi_posisi": "1.\tAdministrasi Penjualan (Sales Administration)\n•\tMembantu input data pelanggan, permintaan layanan, dan penawaran ke sistem administrasi atau spreadsheet.\n•\tMembantu menyiapkan dokumen seperti quotation, form permintaan sertifikasi, surat penawaran, dan laporan penutupan proyek.\n•\tMembantu pengecekan kelengkapan data pelanggan sebelum diteruskan ke bagian operasional atau laboratorium.\n\n2.\tDukungan Proses Sertifikasi dan Pengujian\n•\tMembantu memantau status order (sertifikasi maupun pengujian) dari awal hingga hasil akhir diterbitkan.\n•\tMembantu administrasi pengiriman sampel dan koordinasi dengan tim operasional/laboratorium terkait jadwal pengujian.\n•\tMembantu mempersiapkan dokumen pendukung untuk auditor atau pelanggan, seperti bukti hasil uji atau sertifikat.\n\n3.\tKoordinasi dan Komunikasi Pelanggan\n•\tMembantu menjawab pertanyaan dasar pelanggan (status order, dokumen yang dibutuhkan, estimasi waktu).\n•\tMeneruskan komunikasi yang memerlukan tindak lanjut ke tim Sales Executive atau Supervisor.\n•\tMembantu pencatatan hasil follow-up pelanggan dan update status di sistem CRM atau log pelanggan.\n\n4.\tPengarsipan Dokumen dan Data Penjualan\n•\tMengarsipkan dokumen penawaran, purchase order (PO), dan sertifikat hasil pengujian.\n•\tMembantu melakukan rekap mingguan atau bulanan data penjualan dan progres sertifikasi.\n•\tMenjaga kerapian dan keamanan arsip digital maupun fisik sesuai sistem mutu.\n\n5.\tDukungan Administratif Umum\n•\tMembantu pembuatan laporan administrasi sederhana (misalnya rekap pelanggan aktif, status order, atau quotation).\n•\tMembantu update daftar harga atau template dokumen penawaran.\n•\tMembantu kegiatan persiapan meeting tim sales, seperti mencetak data pelanggan atau laporan capaian.\n\n6.\tKepatuhan dan Etika Kerja\n•\tMenjaga kerahasiaan data pelanggan dan hasil pengujian/sertifikasi.\n•\tMengikuti tata tertib perusahaan serta arahan dari pembimbing lapangan.\n•\tMenunjukkan sikap profesional, teliti, dan komunikatif dalam setiap tugas.",
            "syarat_khusus": null,
            "usia_minimal": null,
            "usia_maksimal": null,
            "revisi": null,
            "id_kondisi_fisik": null,
            "id_program": "9909f286-f3e7-4dec-969b-1d07a2133527",
            "created_at": "2025-10-29 08:08:15",
            "updated_at": null,
            "kode_kbji": null,
            "penempatan": null,
            "id_jenis_kelamin": null,
            "id_status_posisi": 2,
            "jumlah_kuota": 1,
            "jumlah_terdaftar": 1,
            "program_studi": "[{\"id\":\"2f6440b7-d057-40e7-bce1-9a4cf73f441d\",\"title\":\"Manajemen\"},{\"id\":\"2fee5a6d-a685-4a85-911b-5aa7e4980851\",\"title\":\"Teknik Industri\"},{\"id\":\"81ac3445-1d83-4fd1-a326-e3130c3b1ef1\",\"title\":\"Manajemen Administrasi\"},{\"id\":\"e3668d6d-acab-4f65-8d20-262e73fe8f36\",\"title\":\"Manajemen Pemasaran\"},{\"id\":\"2c1f894d-16df-471c-abe7-6939d132c6b0\",\"title\":\"Komunikasi\"}]",
            "jenjang": "[\"Diploma\",\"Sarjana\"]",
            "ref_status_posisi": {
                "id_status_posisi": 2,
                "nama_status_posisi": "Terverifikasi"
            },
            "program": {
                "id_program": "9909f286-f3e7-4dec-969b-1d07a2133527",
                "id_sumber_dana": null,
                "id_perusahaan": "c943b052-81a3-4007-9802-aba7447240bb",
                "id_jadwal": "48039861-1251-474e-86af-d904e829093b"
            },
            "perusahaan": {
                "id_perusahaan": "c943b052-81a3-4007-9802-aba7447240bb",
                "id_desa": null,
                "nama_perusahaan": "Tüv Nord Indonesia",
                "deskripsi_perusahaan": "TÜV NORD Indonesia merupakan perusahaan terkemuka yang bergerak di bidang Inspection, Certification, Testing, dan Training (ICTT). Sebagai bagian dari jaringan global TÜV NORD, kami berkomitmen untuk menghadirkan layanan yang terpercaya, inovatif, serta berbasis pengetahuan guna mendukung keamanan, keberlanjutan, dan kesuksesan para pelanggan di berbagai sektor industri.  Didukung oleh tenaga profesional yang berkompeten serta teknologi yang terkini, TÜV NORD Indonesia menyediakan rangkaian layanan yang komprehensif, meliputi:  Sertifikasi sistem manajemen  Layanan pelatihan  Energi & keberlanjutan  Layanan medis  Jasa inspeksi  Keamanan pangan  Pengujian produk konsumen  Pengujian & pemantauan lingkungan  Higiene industri  Pengujian petrokimia  Kalibrasi peralatan  Pengujian & sertifikasi produk  Dengan cakupan layanan yang luas, kami hadir untuk memberikan solusi yang dapat diandalkan, mendukung daya saing bisnis, sekaligus memastikan standar kualitas dan keamanan terpenuhi sesuai regulasi nasional maupun internasional.  Visi Menjadi mitra terpercaya dalam mewujudkan keamanan, keberhasilan, dan keberlanjutan melalui pengetahuan, serta membangun konektivitas di era digital yang memungkinkan pelayanan teknis, digital, dan terhubung di mana pun dan kapan pun.  Misi  Mengedepankan keunggulan teknologi sebagai landasan utama dalam setiap layanan.  Memberikan hasil yang berorientasi masa depan dan relevan bagi kebutuhan pelanggan.  Menjadikan pengetahuan sebagai kunci untuk menciptakan nilai tambah dan solusi berkelanjutan.  Nilai Perusahaan  Fokus pada pelanggan sebagai prioritas utama dalam memberikan layanan terbaik.  Karyawan sebagai kunci kesuksesan, dengan kompetensi dan dedikasi yang menjadi fondasi pertumbuhan perusahaan.  Dengan semangat inovasi dan orientasi pada masa depan, TÜV NORD Indonesia terus berkomitmen untuk mendukung perkembangan industri, melindungi kepentingan masyarakat, serta mendorong terciptanya standar global yang lebih aman, berkualitas, dan berkelanjutan.",
                "alamat": "Jl. Science Timur 1 Blok. B3-F1 & F2 Kawasan Industri Jababeka V Cikarang\n17530 Bekasi",
                "logo": "https://wlkp-assets.kemnaker.go.id/companies/c943b052-81a3-4007-9802-aba7447240bb/68c3c95369301.jpg",
                "banner": "https://wlkp-assets.kemnaker.go.id/companies/c943b052-81a3-4007-9802-aba7447240bb/68c3cac649983.jpg",
                "created_at": "2025-10-29 08:08:15",
                "updated_at": null,
                "kode_kabupaten": "3216",
                "nama_kabupaten": "KAB. BEKASI",
                "kode_provinsi": "32",
                "nama_provinsi": "JAWA BARAT"
            },
            "jadwal": {
                "id_jadwal": "48039861-1251-474e-86af-d904e829093b",
                "angkatan": "2",
                "tanggal_batas_pendaftaran": "2025-10-03 00:00:00",
                "tanggal_mulai": "2025-11-24 00:00:00",
                "tanggal_selesai": "2026-05-23 23:59:59",
                "tahun": "2025",
                "tanggal_rencana_mulai": "2025-10-24 00:00:00",
                "tanggal_rencana_akhir": "2025-11-11 23:59:59",
                "tanggal_seleksi_mulai": "2025-11-12 00:00:00",
                "tanggal_seleksi_akhir": "2025-11-20 23:59:59",
                "tanggal_usulan_mulai": "2025-10-01 00:00:00",
                "tanggal_usulan_akhir": "2025-10-08 00:00:00",
                "tanggal_persetujuan_awal": "2025-10-05 00:00:00",
                "tanggal_persetujuan_akhir": "2025-10-06 00:00:00",
                "tanggal_pendaftaran_awal": "2025-11-06 00:00:00",
                "tanggal_pendaftaran_akhir": "2025-11-14 23:59:59",
                "tanggal_pengumuman_mulai": "2025-11-14 00:00:00",
                "tanggal_pengumuman_akhir": "2025-11-20 23:59:59",
                "tanggal_lulus_awal": "2024-11-01 00:00:00",
                "tanggal_lulus_akhir": "2025-10-31 00:00:00",
                "publish": 1
            },
            "government_agency": {
                "government_agency_name": null
            },
            "sub_government_agency": {
                "sub_government_agency_name": null
            }
        },
        {
            "id_posisi": "a03c1575-d184-4a22-a4cd-e446b40537cd",
            "posisi": "Customer Service Intern",
            "deskripsi_posisi": "1. Analyze and examine whether claim related data is appropriate. Manage to resolve the issue.\n2.[Warranty and return approval] Approve and manage the claim based on a certain logic. Approve and manage exceptional cases by examining whether the cause is reasonable.\n3. [Unit cost management] Examine whether a new customer’s contracted cost for each product is appropriate and manage to negotiate and decide the amount.\n4. [Credit management] Manage a customer’s claim and payment status. Manage to discuss with relevant departments when issues happen.\n5. [Managing service costs] Manage service costs paid by a customer. Manage to implement an improvement measure.\n6. [Understanding inspection logic] Manage to discuss with relevant departments if there is something wrong with the logic which is required for approving warranty.\n7. [Managing appropriation fund] Manage balance with appropriate and repayment based on the guided rate compared to the revenue.",
            "syarat_khusus": null,
            "usia_minimal": null,
            "usia_maksimal": null,
            "revisi": null,
            "id_kondisi_fisik": null,
            "id_program": "855bd6ea-0433-4108-b36e-75d546f252d4",
            "created_at": "2025-10-14 14:14:38",
            "updated_at": "2025-10-29 09:19:16",
            "kode_kbji": null,
            "penempatan": null,
            "id_jenis_kelamin": null,
            "id_status_posisi": 2,
            "jumlah_kuota": 1,
            "jumlah_terdaftar": 0,
            "program_studi": "[{\"id\":\"2fee5a6d-a685-4a85-911b-5aa7e4980851\",\"title\":\"Teknik Industri\"},{\"id\":\"112d50ec-5feb-4a3f-828e-f024b4d0438d\",\"title\":\"Akuntansi Manajemen\"},{\"id\":\"68cab25f-4830-44a8-97f8-9c7a30b98ffc\",\"title\":\"Bisnis dan Manajemen Ritel\"},{\"id\":\"2f6440b7-d057-40e7-bce1-9a4cf73f441d\",\"title\":\"Manajemen\"},{\"id\":\"254c1344-2364-4d97-98ab-fdbae136a61d\",\"title\":\"Teknik Manajemen Industri\"}]",
            "jenjang": "[\"Sarjana\"]",
            "ref_status_posisi": {
                "id_status_posisi": 2,
                "nama_status_posisi": "Terverifikasi"
            },
            "program": {
                "id_program": "855bd6ea-0433-4108-b36e-75d546f252d4",
                "id_sumber_dana": null,
                "id_perusahaan": "3d6883be-878d-4d03-a1c5-dbd3bdac85f4",
                "id_jadwal": "48039861-1251-474e-86af-d904e829093b"
            },
            "perusahaan": {
                "id_perusahaan": "3d6883be-878d-4d03-a1c5-dbd3bdac85f4",
                "id_desa": null,
                "nama_perusahaan": "PT. Samsung Electronics Indonesia",
                "deskripsi_perusahaan": "PT Samsung Electronics Indonesia adalah perusahaan manufaktur elektronik anak perusahaan dari Samsung Electronics Co., Ltd  yang berkantor pusat di Distrik Yeongtong, Suwon.",
                "alamat": "Jl. Jababeka Raya Blok F29 - 33, Cikarang, Bekasi",
                "logo": "https://wlkp-assets.kemnaker.go.id/companies/3d6883be-878d-4d03-a1c5-dbd3bdac85f4/63eaef79ce38c.png",
                "banner": "https://wlkp-assets.kemnaker.go.id/companies/3d6883be-878d-4d03-a1c5-dbd3bdac85f4/63eaefcadcfdf.jpg",
                "created_at": "2025-10-14 14:14:38",
                "updated_at": "2025-10-29 09:19:16",
                "kode_kabupaten": "3171",
                "nama_kabupaten": "KOTA ADM. JAKARTA PUSAT",
                "kode_provinsi": "31",
                "nama_provinsi": "DKI JAKARTA"
            },
            "jadwal": {
                "id_jadwal": "48039861-1251-474e-86af-d904e829093b",
                "angkatan": "2",
                "tanggal_batas_pendaftaran": "2025-10-03 00:00:00",
                "tanggal_mulai": "2025-11-24 00:00:00",
                "tanggal_selesai": "2026-05-23 23:59:59",
                "tahun": "2025",
                "tanggal_rencana_mulai": "2025-10-24 00:00:00",
                "tanggal_rencana_akhir": "2025-11-11 23:59:59",
                "tanggal_seleksi_mulai": "2025-11-12 00:00:00",
                "tanggal_seleksi_akhir": "2025-11-20 23:59:59",
                "tanggal_usulan_mulai": "2025-10-01 00:00:00",
                "tanggal_usulan_akhir": "2025-10-08 00:00:00",
                "tanggal_persetujuan_awal": "2025-10-05 00:00:00",
                "tanggal_persetujuan_akhir": "2025-10-06 00:00:00",
                "tanggal_pendaftaran_awal": "2025-11-06 00:00:00",
                "tanggal_pendaftaran_akhir": "2025-11-14 23:59:59",
                "tanggal_pengumuman_mulai": "2025-11-14 00:00:00",
                "tanggal_pengumuman_akhir": "2025-11-20 23:59:59",
                "tanggal_lulus_awal": "2024-11-01 00:00:00",
                "tanggal_lulus_akhir": "2025-10-31 00:00:00",
                "publish": 1
            },
            "government_agency": {
                "government_agency_name": null
            },
            "sub_government_agency": {
                "sub_government_agency_name": null
            }
        },
        {
            "id_posisi": "a03c1667-5509-485f-b94a-991bff24d027",
            "posisi": "Digital Communication Intern (Corporate Communication)",
            "deskripsi_posisi": "1. Menangani pengelolaan konten media sosial perusahaan secara end-to-end melalui pengemasan konten yang kreatif dan menarik mulai dari proses perencanaan, pembuatan, penjadwalan, hingga eksekusi dan evaluasi performa konten disesuaikan dengan tipe platform yang digunakan.\n2. Memahami dan mengerti cara menganalisa serta mengevaluasi performa masing-masing platform media sosial perusahaan menggunakan tools tertentu.\n3. Berkolaborasi dengan tim internal untuk memastikan kesesuaian pesan, visual, dan tone komunikasi dengan identitas merek perusahaan.\n4. Membantu memonitor interaksi dan engagement di seluruh kanal digital untuk meningkatkan visibilitas dan citra positif perusahaan.\n5. Mendukung kegiatan komunikasi digital lainnya, termasuk kampanye online, event digital, dan publikasi internal.\n6. Menjalin dan menjaga hubungan baik dengan pihak guna mendukung kegiatan komunikasi perusahaan.",
            "syarat_khusus": null,
            "usia_minimal": null,
            "usia_maksimal": null,
            "revisi": null,
            "id_kondisi_fisik": null,
            "id_program": "7502edf9-fc63-441b-bc05-34e1a8237175",
            "created_at": "2025-10-12 13:03:47",
            "updated_at": "2025-10-29 08:54:06",
            "kode_kbji": null,
            "penempatan": null,
            "id_jenis_kelamin": null,
            "id_status_posisi": 2,
            "jumlah_kuota": 1,
            "jumlah_terdaftar": 3,
            "program_studi": "[{\"id\":\"95dd752e-e00f-4431-90bf-58bdd324a48f\",\"title\":\"Ilmu Komunikasi\"},{\"id\":\"2c1f894d-16df-471c-abe7-6939d132c6b0\",\"title\":\"Komunikasi\"},{\"id\":\"c9672149-95cd-4da9-8825-59fa83030831\",\"title\":\"Hubungan Masyarakat Dan Komunikasi Digital\"},{\"id\":\"8631f68c-a0f0-4758-9251-a62190209909\",\"title\":\"Hubungan Masyarakat\"},{\"id\":\"bef61511-23f4-4602-96e5-1661680bf4de\",\"title\":\"Komunikasi Digital dan Media\"}]",
            "jenjang": "[\"Diploma\",\"Sarjana\"]",
            "ref_status_posisi": {
                "id_status_posisi": 2,
                "nama_status_posisi": "Terverifikasi"
            },
            "program": {
                "id_program": "7502edf9-fc63-441b-bc05-34e1a8237175",
                "id_sumber_dana": null,
                "id_perusahaan": "c26624c0-22a4-4a85-8b8a-8129472abfca",
                "id_jadwal": "48039861-1251-474e-86af-d904e829093b"
            },
            "perusahaan": {
                "id_perusahaan": "c26624c0-22a4-4a85-8b8a-8129472abfca",
                "id_desa": null,
                "nama_perusahaan": "PT Nusantara Infrastructure, Tbk.",
                "deskripsi_perusahaan": "",
                "alamat": "Equity Tower Lt 38, Sudirman Central Business District Jl Jend. Sudirman kav 52 - 53 Lot 9 Jakarta Selatan",
                "logo": "https://wlkp-assets.kemnaker.go.id/companies/c26624c0-22a4-4a85-8b8a-8129472abfca/6900911f90878.png",
                "banner": "",
                "created_at": "2025-10-12 13:03:47",
                "updated_at": "2025-10-29 08:54:06",
                "kode_kabupaten": "3174",
                "nama_kabupaten": "KOTA ADM. JAKARTA SELATAN",
                "kode_provinsi": "31",
                "nama_provinsi": "DKI JAKARTA"
            },
            "jadwal": {
                "id_jadwal": "48039861-1251-474e-86af-d904e829093b",
                "angkatan": "2",
                "tanggal_batas_pendaftaran": "2025-10-03 00:00:00",
                "tanggal_mulai": "2025-11-24 00:00:00",
                "tanggal_selesai": "2026-05-23 23:59:59",
                "tahun": "2025",
                "tanggal_rencana_mulai": "2025-10-24 00:00:00",
                "tanggal_rencana_akhir": "2025-11-11 23:59:59",
                "tanggal_seleksi_mulai": "2025-11-12 00:00:00",
                "tanggal_seleksi_akhir": "2025-11-20 23:59:59",
                "tanggal_usulan_mulai": "2025-10-01 00:00:00",
                "tanggal_usulan_akhir": "2025-10-08 00:00:00",
                "tanggal_persetujuan_awal": "2025-10-05 00:00:00",
                "tanggal_persetujuan_akhir": "2025-10-06 00:00:00",
                "tanggal_pendaftaran_awal": "2025-11-06 00:00:00",
                "tanggal_pendaftaran_akhir": "2025-11-14 23:59:59",
                "tanggal_pengumuman_mulai": "2025-11-14 00:00:00",
                "tanggal_pengumuman_akhir": "2025-11-20 23:59:59",
                "tanggal_lulus_awal": "2024-11-01 00:00:00",
                "tanggal_lulus_akhir": "2025-10-31 00:00:00",
                "publish": 1
            },
            "government_agency": {
                "government_agency_name": null
            },
            "sub_government_agency": {
                "sub_government_agency_name": null
            }
        },
        {
            "id_posisi": "a03c173d-1bd1-456e-b87e-e95bea2bb92f",
            "posisi": "Civil Structure Designer",
            "deskripsi_posisi": "Mampu membuat design struktur dengan benar. Sangat memahami Safety & Structure Integrity. Memiliki kemampuan interpersonal yang baik. Dapat bekerjasama dibawah tekanan sekalipun. Memiliki Integritas dan kemandirian. Mau mempelajari dan melaksanakan hal baru demi kemajuan perusahaan. Memiliki Sertifikasi yang mendukung pekerjaan struktur ini.",
            "syarat_khusus": null,
            "usia_minimal": null,
            "usia_maksimal": null,
            "revisi": null,
            "id_kondisi_fisik": null,
            "id_program": "81f8986c-2055-4f13-bfec-905bbab6411b",
            "created_at": "2025-10-06 09:08:47",
            "updated_at": "2025-10-28 17:14:45",
            "kode_kbji": null,
            "penempatan": null,
            "id_jenis_kelamin": null,
            "id_status_posisi": 2,
            "jumlah_kuota": 1,
            "jumlah_terdaftar": 0,
            "program_studi": "[{\"id\":\"a4cd875c-c20b-42d9-a4da-a634722d42b9\",\"title\":\"Teknik Sipil\"},{\"id\":\"ff80420a-3db9-4a9d-9fa7-c2643433a044\",\"title\":\"Konstruksi Sipil\"},{\"id\":\"128a2af2-1bcf-472a-9a20-fa295848ae56\",\"title\":\"Teknik Konstruksi Sipil\"},{\"id\":\"d9536675-9070-4908-b1aa-610e7d21ffde\",\"title\":\"Teknik Sipil Bangunan Gedung\"},{\"id\":\"f78eb8c5-3f9d-430a-aaa9-b3ba2ecff2e9\",\"title\":\"Teknologi Rekayasa Pelaksanaan Bangunan Sipil\"}]",
            "jenjang": "[\"Sarjana\"]",
            "ref_status_posisi": {
                "id_status_posisi": 2,
                "nama_status_posisi": "Terverifikasi"
            },
            "program": {
                "id_program": "81f8986c-2055-4f13-bfec-905bbab6411b",
                "id_sumber_dana": null,
                "id_perusahaan": "881e3b3d-30cc-49e1-a820-cc6688147557",
                "id_jadwal": "48039861-1251-474e-86af-d904e829093b"
            },
            "perusahaan": {
                "id_perusahaan": "881e3b3d-30cc-49e1-a820-cc6688147557",
                "id_desa": null,
                "nama_perusahaan": "PT. Sindopex Perotama",
                "deskripsi_perusahaan": "PT. Sindopex Perotama dengan hasil produk Hidrogen Peroksida",
                "alamat": "Jl. Raya Kramat Temenggung, Kramattemenggung, Tarik-Sidoarjo",
                "logo": "https://wlkp-assets.kemnaker.go.id/companies/881e3b3d-30cc-49e1-a820-cc6688147557/66b422f6b4433.PNG",
                "banner": "https://wlkp-assets.kemnaker.go.id/companies/881e3b3d-30cc-49e1-a820-cc6688147557/6164f79f18f03.jpg",
                "created_at": "2025-10-06 09:08:47",
                "updated_at": "2025-10-28 17:14:45",
                "kode_kabupaten": "3515",
                "nama_kabupaten": "KAB. SIDOARJO",
                "kode_provinsi": "35",
                "nama_provinsi": "JAWA TIMUR"
            },
            "jadwal": {
                "id_jadwal": "48039861-1251-474e-86af-d904e829093b",
                "angkatan": "2",
                "tanggal_batas_pendaftaran": "2025-10-03 00:00:00",
                "tanggal_mulai": "2025-11-24 00:00:00",
                "tanggal_selesai": "2026-05-23 23:59:59",
                "tahun": "2025",
                "tanggal_rencana_mulai": "2025-10-24 00:00:00",
                "tanggal_rencana_akhir": "2025-11-11 23:59:59",
                "tanggal_seleksi_mulai": "2025-11-12 00:00:00",
                "tanggal_seleksi_akhir": "2025-11-20 23:59:59",
                "tanggal_usulan_mulai": "2025-10-01 00:00:00",
                "tanggal_usulan_akhir": "2025-10-08 00:00:00",
                "tanggal_persetujuan_awal": "2025-10-05 00:00:00",
                "tanggal_persetujuan_akhir": "2025-10-06 00:00:00",
                "tanggal_pendaftaran_awal": "2025-11-06 00:00:00",
                "tanggal_pendaftaran_akhir": "2025-11-14 23:59:59",
                "tanggal_pengumuman_mulai": "2025-11-14 00:00:00",
                "tanggal_pengumuman_akhir": "2025-11-20 23:59:59",
                "tanggal_lulus_awal": "2024-11-01 00:00:00",
                "tanggal_lulus_akhir": "2025-10-31 00:00:00",
                "publish": 1
            },
            "government_agency": {
                "government_agency_name": null
            },
            "sub_government_agency": {
                "sub_government_agency_name": null
            }
        },
        {
            "id_posisi": "a03c1768-5ba6-40d2-a58d-2c490251cf1f",
            "posisi": "Accounting & Tax Intern",
            "deskripsi_posisi": "1. Melakukan proses rekonsiliasi akuntansi dengan menganalisis data debit dan kredit antara anak perusahaan dan induk perusahaan.\n2. Membantu pelaksanaan analisis pajak, termasuk perhitungan dan pembuatan bukti potong sesuai ketentuan PPh 23 dan Pasal 4 Ayat 2.\n3. Mengelola administrasi perpajakan melalui sistem Direktorat Jenderal Pajak (DJP) untuk memastikan kepatuhan dan ketepatan pelaporan.\n4. Mendukung pelaksanaan end-to-end Finance, Accounting, & Tax process, termasuk dokumentasi, pelaporan, dan analisis keuangan.\n5. Membantu perencanaan dan pengorganisasian aktivitas akuntansi dan perpajakan agar seluruh tugas terlaksana sesuai instruksi dan timeline yang ditetapkan.\n6. Berkoordinasi dengan stakeholder internal maupun eksternal untuk memastikan kelancaran proses rekonsiliasi, pelaporan pajak, dan kegiatan keuangan lainnya.",
            "syarat_khusus": null,
            "usia_minimal": null,
            "usia_maksimal": null,
            "revisi": null,
            "id_kondisi_fisik": null,
            "id_program": "7502edf9-fc63-441b-bc05-34e1a8237175",
            "created_at": "2025-10-12 13:03:47",
            "updated_at": "2025-10-29 08:54:06",
            "kode_kbji": null,
            "penempatan": null,
            "id_jenis_kelamin": null,
            "id_status_posisi": 2,
            "jumlah_kuota": 1,
            "jumlah_terdaftar": 1,
            "program_studi": "[{\"id\":\"c13ae920-a48f-4a7c-8c89-2b286a7fc225\",\"title\":\"Akuntansi\"}]",
            "jenjang": "[\"Diploma\",\"Sarjana\"]",
            "ref_status_posisi": {
                "id_status_posisi": 2,
                "nama_status_posisi": "Terverifikasi"
            },
            "program": {
                "id_program": "7502edf9-fc63-441b-bc05-34e1a8237175",
                "id_sumber_dana": null,
                "id_perusahaan": "c26624c0-22a4-4a85-8b8a-8129472abfca",
                "id_jadwal": "48039861-1251-474e-86af-d904e829093b"
            },
            "perusahaan": {
                "id_perusahaan": "c26624c0-22a4-4a85-8b8a-8129472abfca",
                "id_desa": null,
                "nama_perusahaan": "PT Nusantara Infrastructure, Tbk.",
                "deskripsi_perusahaan": "",
                "alamat": "Equity Tower Lt 38, Sudirman Central Business District Jl Jend. Sudirman kav 52 - 53 Lot 9 Jakarta Selatan",
                "logo": "https://wlkp-assets.kemnaker.go.id/companies/c26624c0-22a4-4a85-8b8a-8129472abfca/6900911f90878.png",
                "banner": "",
                "created_at": "2025-10-12 13:03:47",
                "updated_at": "2025-10-29 08:54:06",
                "kode_kabupaten": "3174",
                "nama_kabupaten": "KOTA ADM. JAKARTA SELATAN",
                "kode_provinsi": "31",
                "nama_provinsi": "DKI JAKARTA"
            },
            "jadwal": {
                "id_jadwal": "48039861-1251-474e-86af-d904e829093b",
                "angkatan": "2",
                "tanggal_batas_pendaftaran": "2025-10-03 00:00:00",
                "tanggal_mulai": "2025-11-24 00:00:00",
                "tanggal_selesai": "2026-05-23 23:59:59",
                "tahun": "2025",
                "tanggal_rencana_mulai": "2025-10-24 00:00:00",
                "tanggal_rencana_akhir": "2025-11-11 23:59:59",
                "tanggal_seleksi_mulai": "2025-11-12 00:00:00",
                "tanggal_seleksi_akhir": "2025-11-20 23:59:59",
                "tanggal_usulan_mulai": "2025-10-01 00:00:00",
                "tanggal_usulan_akhir": "2025-10-08 00:00:00",
                "tanggal_persetujuan_awal": "2025-10-05 00:00:00",
                "tanggal_persetujuan_akhir": "2025-10-06 00:00:00",
                "tanggal_pendaftaran_awal": "2025-11-06 00:00:00",
                "tanggal_pendaftaran_akhir": "2025-11-14 23:59:59",
                "tanggal_pengumuman_mulai": "2025-11-14 00:00:00",
                "tanggal_pengumuman_akhir": "2025-11-20 23:59:59",
                "tanggal_lulus_awal": "2024-11-01 00:00:00",
                "tanggal_lulus_akhir": "2025-10-31 00:00:00",
                "publish": 1
            },
            "government_agency": {
                "government_agency_name": null
            },
            "sub_government_agency": {
                "sub_government_agency_name": null
            }
        },
        {
            "id_posisi": "a03c17ab-5f35-44d7-970a-6b3c1fc32c6c",
            "posisi": "Visual Merchandise",
            "deskripsi_posisi": "Bertanggung jawab untuk merancang, mengimplementasikan, dan memelihara tampilan visual toko yang menarik, konsisten dengan identitas merek, serta mendukung peningkatan penjualan melalui strategi penataan produk dan komunikasi visual yang efektif.",
            "syarat_khusus": null,
            "usia_minimal": null,
            "usia_maksimal": null,
            "revisi": null,
            "id_kondisi_fisik": null,
            "id_program": "717839cf-b2b2-4069-be3b-1500ff9b27c1",
            "created_at": "2025-10-30 10:34:30",
            "updated_at": null,
            "kode_kbji": null,
            "penempatan": null,
            "id_jenis_kelamin": null,
            "id_status_posisi": 2,
            "jumlah_kuota": 1,
            "jumlah_terdaftar": 0,
            "program_studi": "[{\"id\":\"9dfcaa37-a44b-4331-87ab-bd32dc1066cb\",\"title\":\"Desain Komunikasi Visual\"}]",
            "jenjang": "[\"Diploma\",\"Sarjana\"]",
            "ref_status_posisi": {
                "id_status_posisi": 2,
                "nama_status_posisi": "Terverifikasi"
            },
            "program": {
                "id_program": "717839cf-b2b2-4069-be3b-1500ff9b27c1",
                "id_sumber_dana": null,
                "id_perusahaan": "a34ac15e-2996-4368-bc6a-02682cdbd139",
                "id_jadwal": "48039861-1251-474e-86af-d904e829093b"
            },
            "perusahaan": {
                "id_perusahaan": "a34ac15e-2996-4368-bc6a-02682cdbd139",
                "id_desa": null,
                "nama_perusahaan": "Matahari Department Store",
                "deskripsi_perusahaan": null,
                "alamat": "68. MDS Malang Town Square, Jl. Veteran No.2",
                "logo": "https://wlkp-assets.kemnaker.go.id/companies/a34ac15e-2996-4368-bc6a-02682cdbd139/64f6a58e01959.png",
                "banner": "https://wlkp-assets.kemnaker.go.id/companies/a34ac15e-2996-4368-bc6a-02682cdbd139/64f6a5874bf55.jpg",
                "created_at": "2025-10-30 10:34:30",
                "updated_at": null,
                "kode_kabupaten": "3573",
                "nama_kabupaten": "KOTA MALANG",
                "kode_provinsi": "35",
                "nama_provinsi": "JAWA TIMUR"
            },
            "jadwal": {
                "id_jadwal": "48039861-1251-474e-86af-d904e829093b",
                "angkatan": "2",
                "tanggal_batas_pendaftaran": "2025-10-03 00:00:00",
                "tanggal_mulai": "2025-11-24 00:00:00",
                "tanggal_selesai": "2026-05-23 23:59:59",
                "tahun": "2025",
                "tanggal_rencana_mulai": "2025-10-24 00:00:00",
                "tanggal_rencana_akhir": "2025-11-11 23:59:59",
                "tanggal_seleksi_mulai": "2025-11-12 00:00:00",
                "tanggal_seleksi_akhir": "2025-11-20 23:59:59",
                "tanggal_usulan_mulai": "2025-10-01 00:00:00",
                "tanggal_usulan_akhir": "2025-10-08 00:00:00",
                "tanggal_persetujuan_awal": "2025-10-05 00:00:00",
                "tanggal_persetujuan_akhir": "2025-10-06 00:00:00",
                "tanggal_pendaftaran_awal": "2025-11-06 00:00:00",
                "tanggal_pendaftaran_akhir": "2025-11-14 23:59:59",
                "tanggal_pengumuman_mulai": "2025-11-14 00:00:00",
                "tanggal_pengumuman_akhir": "2025-11-20 23:59:59",
                "tanggal_lulus_awal": "2024-11-01 00:00:00",
                "tanggal_lulus_akhir": "2025-10-31 00:00:00",
                "publish": 1
            },
            "government_agency": {
                "government_agency_name": null
            },
            "sub_government_agency": {
                "sub_government_agency_name": null
            }
        },
        {
            "id_posisi": "a03c1aad-4104-4916-8c12-48d2472bc6b5",
            "posisi": "TENAGA TEKNIK",
            "deskripsi_posisi": "MERENCANAKAN KEGIATAN PELAKSANAAN PEKERJAAN\nMELAKSANAKAN DAN MEMBUAT LAPORAN KEGIATAN PELAKSANAAN PEKERJAAN\nMENGEVALUASI KENDALA - KENDALA DI LAPANGAN",
            "syarat_khusus": null,
            "usia_minimal": null,
            "usia_maksimal": null,
            "revisi": null,
            "id_kondisi_fisik": null,
            "id_program": "1fde885d-e39a-4a91-b755-ce83488a0e03",
            "created_at": "2025-10-30 11:51:18",
            "updated_at": "2025-10-30 12:10:46",
            "kode_kbji": null,
            "penempatan": null,
            "id_jenis_kelamin": null,
            "id_status_posisi": 2,
            "jumlah_kuota": 1,
            "jumlah_terdaftar": 3,
            "program_studi": "[{\"id\":\"a4cd875c-c20b-42d9-a4da-a634722d42b9\",\"title\":\"Teknik Sipil\"}]",
            "jenjang": "[\"Sarjana\"]",
            "ref_status_posisi": {
                "id_status_posisi": 2,
                "nama_status_posisi": "Terverifikasi"
            },
            "program": {
                "id_program": "1fde885d-e39a-4a91-b755-ce83488a0e03",
                "id_sumber_dana": null,
                "id_perusahaan": "e690d7dc-6eac-403f-b760-77267bae2527",
                "id_jadwal": "48039861-1251-474e-86af-d904e829093b"
            },
            "perusahaan": {
                "id_perusahaan": "e690d7dc-6eac-403f-b760-77267bae2527",
                "id_desa": null,
                "nama_perusahaan": "Solusi Pratama Mandiri",
                "deskripsi_perusahaan": null,
                "alamat": "Dusun Laetua Klolok",
                "logo": null,
                "banner": null,
                "created_at": "2025-10-30 11:51:18",
                "updated_at": "2025-10-30 12:10:46",
                "kode_kabupaten": "5321",
                "nama_kabupaten": "KAB. MALAKA",
                "kode_provinsi": "53",
                "nama_provinsi": "NUSA TENGGARA TIMUR"
            },
            "jadwal": {
                "id_jadwal": "48039861-1251-474e-86af-d904e829093b",
                "angkatan": "2",
                "tanggal_batas_pendaftaran": "2025-10-03 00:00:00",
                "tanggal_mulai": "2025-11-24 00:00:00",
                "tanggal_selesai": "2026-05-23 23:59:59",
                "tahun": "2025",
                "tanggal_rencana_mulai": "2025-10-24 00:00:00",
                "tanggal_rencana_akhir": "2025-11-11 23:59:59",
                "tanggal_seleksi_mulai": "2025-11-12 00:00:00",
                "tanggal_seleksi_akhir": "2025-11-20 23:59:59",
                "tanggal_usulan_mulai": "2025-10-01 00:00:00",
                "tanggal_usulan_akhir": "2025-10-08 00:00:00",
                "tanggal_persetujuan_awal": "2025-10-05 00:00:00",
                "tanggal_persetujuan_akhir": "2025-10-06 00:00:00",
                "tanggal_pendaftaran_awal": "2025-11-06 00:00:00",
                "tanggal_pendaftaran_akhir": "2025-11-14 23:59:59",
                "tanggal_pengumuman_mulai": "2025-11-14 00:00:00",
                "tanggal_pengumuman_akhir": "2025-11-20 23:59:59",
                "tanggal_lulus_awal": "2024-11-01 00:00:00",
                "tanggal_lulus_akhir": "2025-10-31 00:00:00",
                "publish": 1
            },
            "government_agency": {
                "government_agency_name": null
            },
            "sub_government_agency": {
                "sub_government_agency_name": null
            }
        },
        {
            "id_posisi": "a03c1ce9-4d58-45b7-97f5-6b894969ec24",
            "posisi": "Recruitment Internship",
            "deskripsi_posisi": "Mampu merancang dan mengimplementasikan proses recruitment secara end to end.",
            "syarat_khusus": null,
            "usia_minimal": null,
            "usia_maksimal": null,
            "revisi": null,
            "id_kondisi_fisik": null,
            "id_program": "071b0c2d-93d5-4e1a-ab6a-def8a66e0cc3",
            "created_at": "2025-10-30 11:50:11",
            "updated_at": null,
            "kode_kbji": null,
            "penempatan": null,
            "id_jenis_kelamin": null,
            "id_status_posisi": 2,
            "jumlah_kuota": 1,
            "jumlah_terdaftar": 1,
            "program_studi": "[{\"id\":\"3e1f167b-ac1f-4208-b1f7-ff2244791c64\",\"title\":\"Psikologi\"}]",
            "jenjang": "[\"Sarjana\"]",
            "ref_status_posisi": {
                "id_status_posisi": 2,
                "nama_status_posisi": "Terverifikasi"
            },
            "program": {
                "id_program": "071b0c2d-93d5-4e1a-ab6a-def8a66e0cc3",
                "id_sumber_dana": null,
                "id_perusahaan": "08672658-59ae-4be3-83ce-7b8b4a54d2a1",
                "id_jadwal": "48039861-1251-474e-86af-d904e829093b"
            },
            "perusahaan": {
                "id_perusahaan": "08672658-59ae-4be3-83ce-7b8b4a54d2a1",
                "id_desa": null,
                "nama_perusahaan": "So Good Food",
                "deskripsi_perusahaan": "Perusahaan yang bergerak dibidang pengolahan produk daging dan daging unggas",
                "alamat": "JL. DAAN MOGOT KM 12 NO. 9 CENGKARENG - JAKARTA BARAT 11730",
                "logo": "https://wlkp-assets.kemnaker.go.id/companies/08672658-59ae-4be3-83ce-7b8b4a54d2a1/5e3a2879b2adb.jpg",
                "banner": "https://wlkp-assets.kemnaker.go.id/companies/08672658-59ae-4be3-83ce-7b8b4a54d2a1/619c50c71cac7.JPG",
                "created_at": "2025-10-30 11:50:11",
                "updated_at": null,
                "kode_kabupaten": "3173",
                "nama_kabupaten": "KOTA ADM. JAKARTA BARAT",
                "kode_provinsi": "31",
                "nama_provinsi": "DKI JAKARTA"
            },
            "jadwal": {
                "id_jadwal": "48039861-1251-474e-86af-d904e829093b",
                "angkatan": "2",
                "tanggal_batas_pendaftaran": "2025-10-03 00:00:00",
                "tanggal_mulai": "2025-11-24 00:00:00",
                "tanggal_selesai": "2026-05-23 23:59:59",
                "tahun": "2025",
                "tanggal_rencana_mulai": "2025-10-24 00:00:00",
                "tanggal_rencana_akhir": "2025-11-11 23:59:59",
                "tanggal_seleksi_mulai": "2025-11-12 00:00:00",
                "tanggal_seleksi_akhir": "2025-11-20 23:59:59",
                "tanggal_usulan_mulai": "2025-10-01 00:00:00",
                "tanggal_usulan_akhir": "2025-10-08 00:00:00",
                "tanggal_persetujuan_awal": "2025-10-05 00:00:00",
                "tanggal_persetujuan_akhir": "2025-10-06 00:00:00",
                "tanggal_pendaftaran_awal": "2025-11-06 00:00:00",
                "tanggal_pendaftaran_akhir": "2025-11-14 23:59:59",
                "tanggal_pengumuman_mulai": "2025-11-14 00:00:00",
                "tanggal_pengumuman_akhir": "2025-11-20 23:59:59",
                "tanggal_lulus_awal": "2024-11-01 00:00:00",
                "tanggal_lulus_akhir": "2025-10-31 00:00:00",
                "publish": 1
            },
            "government_agency": {
                "government_agency_name": null
            },
            "sub_government_agency": {
                "sub_government_agency_name": null
            }
        },
        {
            "id_posisi": "a03c1d99-8db8-473f-a844-5b796940cf07",
            "posisi": "Operator mesin cnc",
            "deskripsi_posisi": "Deskripsi Pekerjaan\n\nMembantu proses produksi dan pembuatan mould menggunakan mesin CNC milling, CNC lathe, dan EDM.\n\nMenyiapkan bahan kerja (workpiece), memasang benda kerja dan pahat sesuai instruksi teknisi senior.\n\nMembantu proses setting, zero point, dan pengecekan hasil pemesinan.\n\nMelakukan perawatan ringan pada mesin CNC (pembersihan, pengecekan oli, coolant, dan kebersihan area kerja).\n\nMendukung tim mould maker dalam pekerjaan harian dan dokumentasi proses kerja.\n\nMelaporkan hasil kerja dan kendala teknis kepada teknisi senior / supervisor CNC.",
            "syarat_khusus": null,
            "usia_minimal": null,
            "usia_maksimal": null,
            "revisi": null,
            "id_kondisi_fisik": null,
            "id_program": "8d5f6ec4-6609-4ee8-a439-b6ae589f2ed0",
            "created_at": "2025-10-30 11:56:02",
            "updated_at": null,
            "kode_kbji": null,
            "penempatan": null,
            "id_jenis_kelamin": null,
            "id_status_posisi": 2,
            "jumlah_kuota": 1,
            "jumlah_terdaftar": 1,
            "program_studi": "[{\"id\":\"21442969-5763-4416-bb8d-56a80e55ada9\",\"title\":\"Teknik Mesin\"},{\"id\":\"2fee5a6d-a685-4a85-911b-5aa7e4980851\",\"title\":\"Teknik Industri\"}]",
            "jenjang": "[\"Sarjana\",\"Diploma\"]",
            "ref_status_posisi": {
                "id_status_posisi": 2,
                "nama_status_posisi": "Terverifikasi"
            },
            "program": {
                "id_program": "8d5f6ec4-6609-4ee8-a439-b6ae589f2ed0",
                "id_sumber_dana": null,
                "id_perusahaan": "a5b7e3a1-5b48-4968-b50f-91861c82deed",
                "id_jadwal": "48039861-1251-474e-86af-d904e829093b"
            },
            "perusahaan": {
                "id_perusahaan": "a5b7e3a1-5b48-4968-b50f-91861c82deed",
                "id_desa": null,
                "nama_perusahaan": "Mega Jaya Kemas",
                "deskripsi_perusahaan": "Kami memulai perjalanan dengan semangat untuk memberikan solusi kemasan terbaik bagi brand-brand lokal, UMKM, serta perusahaan kosmetik yang ingin tampil profesional dan kompetitif di pasar yang dinamis. Seluruh proses produksi dilakukan dengan standar kontrol kualitas yang ketat, didukung oleh mesin injeksi dan blow molding modern, serta tim teknisi dan operator berpengalaman. Kami memastikan setiap produk yang dihasilkan memiliki konsistensi dimensi, kekuatan material, dan tampilan estetika yang sesuai dengan standar industri kosmetik premium. Kami juga mengembangkan fasilitas in-house mould design & manufacturing, yang memungkinkan kami merancang dan memproduksi mould custom dengan kecepatan dan presisi tinggi. Hal ini memberi kami kendali penuh atas kualitas dan waktu pengerjaan, sehingga klien tidak perlu lagi menunggu lama seperti saat memesan dari luar negeri.",
                "alamat": "PERGUDANGAN CENTRAL INDUSTRIAL PARK BLOK ZETA-KAPPA NO. 14, JL. LINGKAR TIMUR NO. KM 4",
                "logo": "https://wlkp-assets.kemnaker.go.id/companies/a5b7e3a1-5b48-4968-b50f-91861c82deed/6902e8c99ab3b.jpg",
                "banner": "https://wlkp-assets.kemnaker.go.id/companies/a5b7e3a1-5b48-4968-b50f-91861c82deed/6902e8c086f93.jpg",
                "created_at": "2025-10-30 11:56:02",
                "updated_at": null,
                "kode_kabupaten": "3515",
                "nama_kabupaten": "KAB. SIDOARJO",
                "kode_provinsi": "35",
                "nama_provinsi": "JAWA TIMUR"
            },
            "jadwal": {
                "id_jadwal": "48039861-1251-474e-86af-d904e829093b",
                "angkatan": "2",
                "tanggal_batas_pendaftaran": "2025-10-03 00:00:00",
                "tanggal_mulai": "2025-11-24 00:00:00",
                "tanggal_selesai": "2026-05-23 23:59:59",
                "tahun": "2025",
                "tanggal_rencana_mulai": "2025-10-24 00:00:00",
                "tanggal_rencana_akhir": "2025-11-11 23:59:59",
                "tanggal_seleksi_mulai": "2025-11-12 00:00:00",
                "tanggal_seleksi_akhir": "2025-11-20 23:59:59",
                "tanggal_usulan_mulai": "2025-10-01 00:00:00",
                "tanggal_usulan_akhir": "2025-10-08 00:00:00",
                "tanggal_persetujuan_awal": "2025-10-05 00:00:00",
                "tanggal_persetujuan_akhir": "2025-10-06 00:00:00",
                "tanggal_pendaftaran_awal": "2025-11-06 00:00:00",
                "tanggal_pendaftaran_akhir": "2025-11-14 23:59:59",
                "tanggal_pengumuman_mulai": "2025-11-14 00:00:00",
                "tanggal_pengumuman_akhir": "2025-11-20 23:59:59",
                "tanggal_lulus_awal": "2024-11-01 00:00:00",
                "tanggal_lulus_akhir": "2025-10-31 00:00:00",
                "publish": 1
            },
            "government_agency": {
                "government_agency_name": null
            },
            "sub_government_agency": {
                "sub_government_agency_name": null
            }
        },
        {
            "id_posisi": "a03c1e06-6e7a-4f4f-abfb-20474c46e396",
            "posisi": "Commis",
            "deskripsi_posisi": "membantu koki senior (chef de partie) dengan tugas-tugas dasar di dapur, seperti menyiapkan bahan makanan, memasak hidangan dasar, menjaga kebersihan area kerja, dan memastikan operasional dapur berjalan lancar",
            "syarat_khusus": null,
            "usia_minimal": null,
            "usia_maksimal": null,
            "revisi": null,
            "id_kondisi_fisik": null,
            "id_program": "96027fad-335a-43db-9af2-1bb16be6cb7c",
            "created_at": "2025-10-30 11:50:36",
            "updated_at": null,
            "kode_kbji": null,
            "penempatan": null,
            "id_jenis_kelamin": null,
            "id_status_posisi": 2,
            "jumlah_kuota": 1,
            "jumlah_terdaftar": 0,
            "program_studi": "[{\"id\":\"43be1f0e-b279-448d-b448-5a53ec9c3ebd\",\"title\":\"Perhotelan\"}]",
            "jenjang": "[\"Diploma\"]",
            "ref_status_posisi": {
                "id_status_posisi": 2,
                "nama_status_posisi": "Terverifikasi"
            },
            "program": {
                "id_program": "96027fad-335a-43db-9af2-1bb16be6cb7c",
                "id_sumber_dana": null,
                "id_perusahaan": "2da94f88-5875-4337-8e58-2235907c9f78",
                "id_jadwal": "48039861-1251-474e-86af-d904e829093b"
            },
            "perusahaan": {
                "id_perusahaan": "2da94f88-5875-4337-8e58-2235907c9f78",
                "id_desa": null,
                "nama_perusahaan": "Zmp Bali Partners",
                "deskripsi_perusahaan": null,
                "alamat": "Jalan By Pass Ngurah Rai No. 234",
                "logo": null,
                "banner": null,
                "created_at": "2025-10-30 11:50:36",
                "updated_at": null,
                "kode_kabupaten": "5103",
                "nama_kabupaten": "KAB. BADUNG",
                "kode_provinsi": "51",
                "nama_provinsi": "BALI"
            },
            "jadwal": {
                "id_jadwal": "48039861-1251-474e-86af-d904e829093b",
                "angkatan": "2",
                "tanggal_batas_pendaftaran": "2025-10-03 00:00:00",
                "tanggal_mulai": "2025-11-24 00:00:00",
                "tanggal_selesai": "2026-05-23 23:59:59",
                "tahun": "2025",
                "tanggal_rencana_mulai": "2025-10-24 00:00:00",
                "tanggal_rencana_akhir": "2025-11-11 23:59:59",
                "tanggal_seleksi_mulai": "2025-11-12 00:00:00",
                "tanggal_seleksi_akhir": "2025-11-20 23:59:59",
                "tanggal_usulan_mulai": "2025-10-01 00:00:00",
                "tanggal_usulan_akhir": "2025-10-08 00:00:00",
                "tanggal_persetujuan_awal": "2025-10-05 00:00:00",
                "tanggal_persetujuan_akhir": "2025-10-06 00:00:00",
                "tanggal_pendaftaran_awal": "2025-11-06 00:00:00",
                "tanggal_pendaftaran_akhir": "2025-11-14 23:59:59",
                "tanggal_pengumuman_mulai": "2025-11-14 00:00:00",
                "tanggal_pengumuman_akhir": "2025-11-20 23:59:59",
                "tanggal_lulus_awal": "2024-11-01 00:00:00",
                "tanggal_lulus_akhir": "2025-10-31 00:00:00",
                "publish": 1
            },
            "government_agency": {
                "government_agency_name": null
            },
            "sub_government_agency": {
                "sub_government_agency_name": null
            }
        },
        {
            "id_posisi": "a03c1ea2-e662-4226-ab48-db7138f1219c",
            "posisi": "Marcomm",
            "deskripsi_posisi": "Membantu staff Marketing dalam penanganan administrasi Mall",
            "syarat_khusus": null,
            "usia_minimal": null,
            "usia_maksimal": null,
            "revisi": null,
            "id_kondisi_fisik": null,
            "id_program": "2b29c1ca-9f64-4169-b863-ea63d084422a",
            "created_at": "2025-10-14 22:05:45",
            "updated_at": "2025-10-30 10:37:29",
            "kode_kbji": null,
            "penempatan": null,
            "id_jenis_kelamin": null,
            "id_status_posisi": 2,
            "jumlah_kuota": 1,
            "jumlah_terdaftar": 5,
            "program_studi": "[{\"id\":\"e12302ac-c8dc-4d0a-90a7-402f6fafd27e\",\"title\":\"Manajemen Pemasaran\\/Marketing\"}]",
            "jenjang": "[\"Diploma\",\"Sarjana\"]",
            "ref_status_posisi": {
                "id_status_posisi": 2,
                "nama_status_posisi": "Terverifikasi"
            },
            "program": {
                "id_program": "2b29c1ca-9f64-4169-b863-ea63d084422a",
                "id_sumber_dana": null,
                "id_perusahaan": "652311d7-ecc6-41bd-8d68-626ba49b6ca2",
                "id_jadwal": "48039861-1251-474e-86af-d904e829093b"
            },
            "perusahaan": {
                "id_perusahaan": "652311d7-ecc6-41bd-8d68-626ba49b6ca2",
                "id_desa": null,
                "nama_perusahaan": "PT. Maju Batu Bersama / Jawa Timur Park 3",
                "deskripsi_perusahaan": "Jatim Park 3 dibangun dengan mengandalkan teknologi tinggi. Menghadirkan 3 zone utama, yaitu Museum patung lilin, museum musik, dan yang paling populer Taman dinosaurus.",
                "alamat": "JL. IR. SOEKARNO RT 04 RW 06 DS. BEJI KEC. JUNREJO KOTA BATU",
                "logo": "https://wlkp-assets.kemnaker.go.id/companies/652311d7-ecc6-41bd-8d68-626ba49b6ca2/60125db2864f7.jpg",
                "banner": "https://wlkp-assets.kemnaker.go.id/companies/652311d7-ecc6-41bd-8d68-626ba49b6ca2/60125dbf997c5.jpg",
                "created_at": "2025-10-14 22:05:45",
                "updated_at": "2025-10-30 10:37:29",
                "kode_kabupaten": "3579",
                "nama_kabupaten": "KOTA BATU",
                "kode_provinsi": "35",
                "nama_provinsi": "JAWA TIMUR"
            },
            "jadwal": {
                "id_jadwal": "48039861-1251-474e-86af-d904e829093b",
                "angkatan": "2",
                "tanggal_batas_pendaftaran": "2025-10-03 00:00:00",
                "tanggal_mulai": "2025-11-24 00:00:00",
                "tanggal_selesai": "2026-05-23 23:59:59",
                "tahun": "2025",
                "tanggal_rencana_mulai": "2025-10-24 00:00:00",
                "tanggal_rencana_akhir": "2025-11-11 23:59:59",
                "tanggal_seleksi_mulai": "2025-11-12 00:00:00",
                "tanggal_seleksi_akhir": "2025-11-20 23:59:59",
                "tanggal_usulan_mulai": "2025-10-01 00:00:00",
                "tanggal_usulan_akhir": "2025-10-08 00:00:00",
                "tanggal_persetujuan_awal": "2025-10-05 00:00:00",
                "tanggal_persetujuan_akhir": "2025-10-06 00:00:00",
                "tanggal_pendaftaran_awal": "2025-11-06 00:00:00",
                "tanggal_pendaftaran_akhir": "2025-11-14 23:59:59",
                "tanggal_pengumuman_mulai": "2025-11-14 00:00:00",
                "tanggal_pengumuman_akhir": "2025-11-20 23:59:59",
                "tanggal_lulus_awal": "2024-11-01 00:00:00",
                "tanggal_lulus_akhir": "2025-10-31 00:00:00",
                "publish": 1
            },
            "government_agency": {
                "government_agency_name": null
            },
            "sub_government_agency": {
                "sub_government_agency_name": null
            }
        },
        {
            "id_posisi": "a03c1f10-228e-46c9-aeed-b3c0e7ccfe6f",
            "posisi": "Magang Akuntansi - Departemen Tata Kelola dan Kepatuhan",
            "deskripsi_posisi": "Kualifikasi:\n1. Pendidikan minimal S1 jurusan Akuntansi;\n2. Pengalaman (Magang/PKWT di bidang Akuntansi);\n3. Memiliki sikap disiplin, dan integritas;\n4. Memiliki kemampuan komunikasi interpersonal yang baik;\n5. Memiliki keahlian dalam menggunakan Teknologi Informasi;\n6. Memiliki pemahaman yang baik terkait Tata Kelola, Manajemen Risiko dan Kepatuhan;\n7. Memiliki pemahaman yang baik terkait Laporan Keuangan;\n8. Memiliki kemampuan Analisis Data.\n\nJobDesc:\n1.\tMendokumentasikan dan memetakan hasil rekomendasi Internal Control Over Financial Report (ICoFR) per unit kerja;\n2.\tMelaksanakan analisis kuantitatif dalam scoping implementasi ICoFR;\n3.\tMelakukan pendampingan pada Unit Kerja dalam penyusunan Control Self Assessment (CSA) Implementasi ICoFR (Kewajiban Peruri sesuai SK-5);\n4.\tMembantu dalam melaksanakan evaluasi hasil ICoFR ke masing-masing unit kerja 2x dalam 1 tahun (Kewajiban Peruri sesuai SK-5);\n5.\tMembantu dalam pelaksanaan kegiatan internal control testing (Kewajiban Peruri sesuai SK-7);\n6.\tMenyusun dan menyampaikan laporan bulanan/triwulanan/tahunan terkait ICoFR secara berkala kepada stakeholder yang berkaitan.",
            "syarat_khusus": null,
            "usia_minimal": null,
            "usia_maksimal": null,
            "revisi": null,
            "id_kondisi_fisik": null,
            "id_program": "06e11858-71b8-4005-b8e8-fd3a6df22494",
            "created_at": "2025-10-27 14:07:38",
            "updated_at": "2025-10-30 07:48:33",
            "kode_kbji": null,
            "penempatan": null,
            "id_jenis_kelamin": null,
            "id_status_posisi": 2,
            "jumlah_kuota": 1,
            "jumlah_terdaftar": 4,
            "program_studi": "[{\"id\":\"c13ae920-a48f-4a7c-8c89-2b286a7fc225\",\"title\":\"Akuntansi\"}]",
            "jenjang": "[\"Sarjana\"]",
            "ref_status_posisi": {
                "id_status_posisi": 2,
                "nama_status_posisi": "Terverifikasi"
            },
            "program": {
                "id_program": "06e11858-71b8-4005-b8e8-fd3a6df22494",
                "id_sumber_dana": null,
                "id_perusahaan": "d5c9bf39-b11e-41a8-b219-3f704aac1899",
                "id_jadwal": "48039861-1251-474e-86af-d904e829093b"
            },
            "perusahaan": {
                "id_perusahaan": "d5c9bf39-b11e-41a8-b219-3f704aac1899",
                "id_desa": null,
                "nama_perusahaan": "Perum Percetakan Uang Ri",
                "deskripsi_perusahaan": "Di dalam perjalanan sejarahnya, Peruri mencatat beberapa milestone yang membawa nama Negara Kesatuan Republik Indonesia (NKRI) sebagai berikut: (i). Pada 1982, menjadi tuan rumah Konferensi Pencetakan Uang Logam Asia Tenggara (TEMAN, Technical Meeting of Mints in ASEAN); (ii). Pada 1983, menjadi tuan rumah Konferensi Pencetakan Uang Kertas Asia Pasifik ke-6 (PRBPC, Pacific Rim Banknote Printers Conference); (iii). Pada 1983, pemancangan tiang pertama pembangunan gedung pencetakan uang di Karawang oleh Menteri Keuangan; (iv). Pada 1994, mesin baru satu lini mulai beroperasi di Kawasan Produksi Peruri Karawang; (v). Pada 2003, penandatangan joint venture agreement (JVA) dengan SICPA, SA (Swiss), produsen tinta uang untuk membentuk perusahaan afiliasi dengan lokasi di Kawasan Produksi Peruri Karawang; (vi). Pada 2005, Presiden RI, Soesilo Bambang Yudhoyono meresmikan Kawasan Produksi Peruri di Karawang. Selanjutnya Peruri masih mencatat beberapa milestone lain, baik terkait dengan corporate action maupun event internasional. Beberapa di  antaranya pada 2011 mendirikan anak perusahaan PWT dan PDS sedangkan pada 2012 mengakuisi PTKP dari status sebelumnya BUMN menjadi anak perusahaan Peruri.   Pada 2013, Peruri kembali menjadi tuan rumah PRBPC ke-20 setelah sebelumnya sukses menyelenggarakan event yang sama pada 1983. Demikian juga dengan konferensi TEMAN, kembali menjadi tuan rumah pada 2015 dengan peserta negara-negara ASEAN dan beberapa negara Eropa, Asia lainnya, Amerika Serikat dan Kanada. Pada 2014, Peruri ditetapkan sebagai BUMN dengan kategori Objek Vital Nasional sektor industri sesuai Keputusan Menteri Perindustrian Nomor 466/M-IND/Kep/8/2014. Pada 2014 juga, Peruri menambah gedung untuk mesin satu lini uang kertas di Karawang.   Menyadari bahwa lingkungan bisnis terus berubah, akhir 2014 manajemen Peruri mencanangkan program transformasi perusahaan dengan membaginya ke dalam 4 (empat) tahapan, yaitu transformasi sumber daya manusia (SDM), bisnis, struktur & sistem serta kultur/budaya. Transformasi perusahaan dipandang sangat penting untuk menggugah dan mengajak karyawan segera berubah dari kondisi comfort zone menuju ke dynamic zone yang lebih kompetitif. Transformasi SDM menjadi pilihan utama untuk dijalankan karena jika kualitas SDM baik secara skill, kompetensi maupun semangatnya maka transformasi lainnya akan berjalan dengan baik pula.  Sejauh ini skill dan kompetensi SDM cukup memadai untuk menjalankan bisnis security printing sesuai amanat PP 06 Tahun 2019 dimaksud tetapi menyongsong berlakunya Masyarakat Ekonomi Asean (MEA), kompetensi \"cukup\" saja masih kurang. Dalam era persaingan yang ketat, kompetensi yang dimiliki harus yang terbaik. Oleh karena itu langkah yang perlu dilakukan adalah merubah mind set dan mendorong terjadinya paradigm shift agar seluruh insan Peruri lebih fokus kepada customer, concern terhadap kepentingan pemilik modal untuk menjalankan perusahaan dengan prinsip-prinsip good corporate governance. Intinya adalah perusahaan ini harus dioperasikan dengan spirit yang tinggi, karakter yang tangguh dan strategi yang tepat.  Transformasi bisnis adalah langkah berikutnya yang menjadi fokus manajemen dengan dasar business road map 4 (empat) Pilar dan 5 (lima) Inisiatif Strategi. Empat Pilar itu terdiri dari pengembangan core business berupa portofolio uang, non uang (pita cukai, paspor, buku tanah, meterai dan dokumen sekuriti lainnya) yang harus secara terus menerus mampu mengadaptasi berbagai perkembangan fitur sekuriti, trend teknologi yang sesuai kebutuhan pelanggan, new wave berupa pengembangan digital business dan non core dalam bentuk optimalisasi aset properti agar produktif. Empat Pilar itu dilengkapi dengan 5 (lima) Insisiatif Strategi, yaitu pengembangan core business, new wave, non core yang didukung oleh pengelolaan dengan didasarkan kepada prinsip-prinsip compliance & good corporate governance (GCG) serta transformasi perusahaan berkelanjutan.  Transformasi struktur & sistem merupakan langkah yang harus selalu sejalan dengan transformasi SDM dan bisnis karena perubahan yang terjadi, perlu dilengkapi dengan  business process re-engeenering yang konsisten. Manajemen Peruri sangat menyadari bahwa penataan struktur & sistem merupakan point penting untuk dilaksanakan karena itu akan menjadi bagian tidak terpisahkan dari berjalannya fungsi compliance & GCG. Pada akhirnya dengan struktur & sistem yang baik maka akan terbentuk kultur/budaya yang baik pula.   Transformasi kultur/budaya pada dasarnya merupakan kristalisasi nilai-nilai yang sifatnya inovatif, yaitu muncul iklim kerja dengan toleransi tinggi/kritis, semangat kerja sama tim tinggi, kejelasan pekerjaan tinggi, semangat kompetensi tinggi, terbuka dan pro-aktif, lebih transparan, informasi lebih terbuka, komunikasi lebih efektif dan kaya dengan pemberdayaan dalam konteks learning organization yang sehat. Terkait dengan kristalisasi nilai-nilai yang sejalan dengan transformasi perusahaan, manajemen perusahaan mengharapkan munculnya SDM yang mempunyai spirit, karakter, integritas, antusias, totalitas dan strategi yang hebat. Nilai-nilai yang ditanamkan di dalam transformasi bisnis, manajemen menekankan agar karyawan mempunyai loyalitas dan komitmen  kepada pekerjaannya, fokus kepada customer, giat melakukan modernisasi alat kerja dan siap melakukan restrukturisasi bisnis agar lebih kompetitif di pasar. Terkait dengan nilai-nilai dari transformasi struktur & sistem, manajemen memutuskan bahwa Peruri harus bekerja dengan dasar sistem information technology (IT) yang governance agar dapat bekerja dengan cepat, tepat, efisien dengan dilandasi knowledge management yang baik.",
                "alamat": "Jl. Palatehan No. 4, Blok K-V, Kebayoran Baru, Jakarta 12160",
                "logo": "https://wlkp-assets.kemnaker.go.id/companies/d5c9bf39-b11e-41a8-b219-3f704aac1899/68ff1ec7475f6.png",
                "banner": "https://wlkp-assets.kemnaker.go.id/companies/d5c9bf39-b11e-41a8-b219-3f704aac1899/612c7efb789e1.jpg",
                "created_at": "2025-10-27 14:07:38",
                "updated_at": "2025-10-30 07:48:33",
                "kode_kabupaten": "3174",
                "nama_kabupaten": "KOTA ADM. JAKARTA SELATAN",
                "kode_provinsi": "31",
                "nama_provinsi": "DKI JAKARTA"
            },
            "jadwal": {
                "id_jadwal": "48039861-1251-474e-86af-d904e829093b",
                "angkatan": "2",
                "tanggal_batas_pendaftaran": "2025-10-03 00:00:00",
                "tanggal_mulai": "2025-11-24 00:00:00",
                "tanggal_selesai": "2026-05-23 23:59:59",
                "tahun": "2025",
                "tanggal_rencana_mulai": "2025-10-24 00:00:00",
                "tanggal_rencana_akhir": "2025-11-11 23:59:59",
                "tanggal_seleksi_mulai": "2025-11-12 00:00:00",
                "tanggal_seleksi_akhir": "2025-11-20 23:59:59",
                "tanggal_usulan_mulai": "2025-10-01 00:00:00",
                "tanggal_usulan_akhir": "2025-10-08 00:00:00",
                "tanggal_persetujuan_awal": "2025-10-05 00:00:00",
                "tanggal_persetujuan_akhir": "2025-10-06 00:00:00",
                "tanggal_pendaftaran_awal": "2025-11-06 00:00:00",
                "tanggal_pendaftaran_akhir": "2025-11-14 23:59:59",
                "tanggal_pengumuman_mulai": "2025-11-14 00:00:00",
                "tanggal_pengumuman_akhir": "2025-11-20 23:59:59",
                "tanggal_lulus_awal": "2024-11-01 00:00:00",
                "tanggal_lulus_akhir": "2025-10-31 00:00:00",
                "publish": 1
            },
            "government_agency": {
                "government_agency_name": null
            },
            "sub_government_agency": {
                "sub_government_agency_name": null
            }
        },
        {
            "id_posisi": "a03c1f27-8fad-4145-87c2-ddfbde3a1e0a",
            "posisi": "Admin Office",
            "deskripsi_posisi": "Membantu kelancaran tim office di hotel dalam melakukan input data, mengelola data, menjaga kerahasian data sehingga operational hotel dari segi administrasi dapat berjalan lancar",
            "syarat_khusus": null,
            "usia_minimal": null,
            "usia_maksimal": null,
            "revisi": null,
            "id_kondisi_fisik": null,
            "id_program": "96027fad-335a-43db-9af2-1bb16be6cb7c",
            "created_at": "2025-10-30 11:50:36",
            "updated_at": null,
            "kode_kbji": null,
            "penempatan": null,
            "id_jenis_kelamin": null,
            "id_status_posisi": 2,
            "jumlah_kuota": 1,
            "jumlah_terdaftar": 0,
            "program_studi": "[{\"id\":\"9889a8b6-d54b-41c7-b83b-f591a55ca812\",\"title\":\"Manajemen Perhotelan dan Pariwisata\"}]",
            "jenjang": "[\"Diploma\",\"Sarjana\"]",
            "ref_status_posisi": {
                "id_status_posisi": 2,
                "nama_status_posisi": "Terverifikasi"
            },
            "program": {
                "id_program": "96027fad-335a-43db-9af2-1bb16be6cb7c",
                "id_sumber_dana": null,
                "id_perusahaan": "2da94f88-5875-4337-8e58-2235907c9f78",
                "id_jadwal": "48039861-1251-474e-86af-d904e829093b"
            },
            "perusahaan": {
                "id_perusahaan": "2da94f88-5875-4337-8e58-2235907c9f78",
                "id_desa": null,
                "nama_perusahaan": "Zmp Bali Partners",
                "deskripsi_perusahaan": null,
                "alamat": "Jalan By Pass Ngurah Rai No. 234",
                "logo": null,
                "banner": null,
                "created_at": "2025-10-30 11:50:36",
                "updated_at": null,
                "kode_kabupaten": "5103",
                "nama_kabupaten": "KAB. BADUNG",
                "kode_provinsi": "51",
                "nama_provinsi": "BALI"
            },
            "jadwal": {
                "id_jadwal": "48039861-1251-474e-86af-d904e829093b",
                "angkatan": "2",
                "tanggal_batas_pendaftaran": "2025-10-03 00:00:00",
                "tanggal_mulai": "2025-11-24 00:00:00",
                "tanggal_selesai": "2026-05-23 23:59:59",
                "tahun": "2025",
                "tanggal_rencana_mulai": "2025-10-24 00:00:00",
                "tanggal_rencana_akhir": "2025-11-11 23:59:59",
                "tanggal_seleksi_mulai": "2025-11-12 00:00:00",
                "tanggal_seleksi_akhir": "2025-11-20 23:59:59",
                "tanggal_usulan_mulai": "2025-10-01 00:00:00",
                "tanggal_usulan_akhir": "2025-10-08 00:00:00",
                "tanggal_persetujuan_awal": "2025-10-05 00:00:00",
                "tanggal_persetujuan_akhir": "2025-10-06 00:00:00",
                "tanggal_pendaftaran_awal": "2025-11-06 00:00:00",
                "tanggal_pendaftaran_akhir": "2025-11-14 23:59:59",
                "tanggal_pengumuman_mulai": "2025-11-14 00:00:00",
                "tanggal_pengumuman_akhir": "2025-11-20 23:59:59",
                "tanggal_lulus_awal": "2024-11-01 00:00:00",
                "tanggal_lulus_akhir": "2025-10-31 00:00:00",
                "publish": 1
            },
            "government_agency": {
                "government_agency_name": null
            },
            "sub_government_agency": {
                "sub_government_agency_name": null
            }
        }
    ],
    "meta": {
        "pagination": {
            "current_page": 386,
            "first_page_url": null,
            "from": 7701,
            "last_page": 789,
            "last_page_url": null,
            "links": null,
            "next_page_url": null,
            "path": null,
            "per_page": 20,
            "prev_page_url": null,
            "to": 7720,
            "total": 15761
        }
    }
}