{
    "data": [
        {
            "id_posisi": "a04896d8-db8c-4f3c-b905-fa019ca1cb97",
            "posisi": "Staf pendukung Teknologi Informatika",
            "deskripsi_posisi": "1.        Mendesain struktur penyimpanan file digital yang terintegrasi dengan sistem tata naskah dinas elektronik\nOutput yang Dihasilkan:\n•        Database kepegawaian yang ter-update dan terdokumentasi digital.\n•        Folder digitalisasi arsip dengan struktur klasifikasi dokumen yang rapi.\n•        Template surat dan nota dinas otomatis (format digital).\n2.        Pengelolaan Website dan Konten Informasi Internal\nOutput yang Dihasilkan:\n•        Website atau halaman informasi internal yang terbarui.\n•        Materi visualisasi kegiatan (banner, infografik, publikasi digital)",
            "syarat_khusus": null,
            "usia_minimal": null,
            "usia_maksimal": null,
            "revisi": null,
            "id_kondisi_fisik": null,
            "id_program": "3897ee41-13d3-4dde-9e7e-7c693882fca7",
            "created_at": "2025-11-05 12:50:45",
            "updated_at": "2025-11-05 17:10:45",
            "kode_kbji": null,
            "penempatan": null,
            "id_jenis_kelamin": null,
            "id_status_posisi": 2,
            "jumlah_kuota": 1,
            "jumlah_terdaftar": 0,
            "program_studi": "[{\"id\":\"0c353635-be19-41e3-abef-287c8fd73d32\",\"title\":\"Teknologi Informasi\"}]",
            "jenjang": "[\"Sarjana\"]",
            "ref_status_posisi": {
                "id_status_posisi": 2,
                "nama_status_posisi": "Terverifikasi"
            },
            "program": {
                "id_program": "3897ee41-13d3-4dde-9e7e-7c693882fca7",
                "id_sumber_dana": null,
                "id_perusahaan": "cce6abbc-dedb-4d86-8d31-9a0b007f4976",
                "id_jadwal": "48039861-1251-474e-86af-d904e829093b"
            },
            "perusahaan": {
                "id_perusahaan": "cce6abbc-dedb-4d86-8d31-9a0b007f4976",
                "id_desa": null,
                "nama_perusahaan": "Sekretariat Jenderal",
                "deskripsi_perusahaan": null,
                "alamat": "Jalan Medan Merdeka Utara No 7",
                "logo": "https://maganghub.kemnaker.go.id/be/v1/storage/uploads/logo/2025/11/PRrb3JNQaRRN1aRzeePn2d1XwXhVbeQuEXZxYrtV.jpg",
                "banner": null,
                "created_at": "2025-11-05 12:50:45",
                "updated_at": "2025-11-05 17:10:45",
                "kode_kabupaten": "3171",
                "nama_kabupaten": "KOTA ADM. JAKARTA PUSAT",
                "kode_provinsi": "31",
                "nama_provinsi": "DKI JAKARTA"
            },
            "jadwal": {
                "id_jadwal": "48039861-1251-474e-86af-d904e829093b",
                "angkatan": "2",
                "tanggal_batas_pendaftaran": "2025-10-03 00:00:00",
                "tanggal_mulai": "2025-11-24 00:00:00",
                "tanggal_selesai": "2026-05-23 23:59:59",
                "tahun": "2025",
                "tanggal_rencana_mulai": "2025-10-24 00:00:00",
                "tanggal_rencana_akhir": "2025-11-11 23:59:59",
                "tanggal_seleksi_mulai": "2025-11-12 00:00:00",
                "tanggal_seleksi_akhir": "2025-11-20 23:59:59",
                "tanggal_usulan_mulai": "2025-10-01 00:00:00",
                "tanggal_usulan_akhir": "2025-10-08 00:00:00",
                "tanggal_persetujuan_awal": "2025-10-05 00:00:00",
                "tanggal_persetujuan_akhir": "2025-10-06 00:00:00",
                "tanggal_pendaftaran_awal": "2025-11-06 00:00:00",
                "tanggal_pendaftaran_akhir": "2025-11-14 23:59:59",
                "tanggal_pengumuman_mulai": "2025-11-14 00:00:00",
                "tanggal_pengumuman_akhir": "2025-11-20 23:59:59",
                "tanggal_lulus_awal": "2024-11-01 00:00:00",
                "tanggal_lulus_akhir": "2025-10-31 00:00:00",
                "publish": 1
            },
            "government_agency": {
                "government_agency_name": "Kementerian Dalam Negeri"
            },
            "sub_government_agency": {
                "sub_government_agency_name": "Sekretariat Jenderal"
            }
        },
        {
            "id_posisi": "a04896e8-31d2-4d0a-8f7c-95ea4039b125",
            "posisi": "Staff Produksi",
            "deskripsi_posisi": "Perencanaan produksi, pengawasan proses produksi, Pengendalian Kualitas & Produktivitas, Koordinasi Antar Departemen, Administrasi & Pelaporan, Pembinaan & Pengembangan Tim",
            "syarat_khusus": null,
            "usia_minimal": null,
            "usia_maksimal": null,
            "revisi": null,
            "id_kondisi_fisik": null,
            "id_program": "d4a637e1-d7a8-4069-b4aa-fc1a3f2e32b3",
            "created_at": "2025-10-10 16:42:57",
            "updated_at": "2025-10-29 14:58:15",
            "kode_kbji": null,
            "penempatan": null,
            "id_jenis_kelamin": null,
            "id_status_posisi": 2,
            "jumlah_kuota": 1,
            "jumlah_terdaftar": 1,
            "program_studi": "[{\"id\":\"2fee5a6d-a685-4a85-911b-5aa7e4980851\",\"title\":\"Teknik Industri\"},{\"id\":\"588f15f5-fb46-459f-a554-703fac78179f\",\"title\":\"Manajemen Industri\"},{\"id\":\"254c1344-2364-4d97-98ab-fdbae136a61d\",\"title\":\"Teknik Manajemen Industri\"},{\"id\":\"c13ae920-a48f-4a7c-8c89-2b286a7fc225\",\"title\":\"Akuntansi\"},{\"id\":\"702dfd8b-b5b8-40fb-843b-4d503451b314\",\"title\":\"Ekonomi\"}]",
            "jenjang": "[\"Sarjana\"]",
            "ref_status_posisi": {
                "id_status_posisi": 2,
                "nama_status_posisi": "Terverifikasi"
            },
            "program": {
                "id_program": "d4a637e1-d7a8-4069-b4aa-fc1a3f2e32b3",
                "id_sumber_dana": null,
                "id_perusahaan": "dd5b3f22-45d7-446f-95c7-907c5b8d4bb1",
                "id_jadwal": "48039861-1251-474e-86af-d904e829093b"
            },
            "perusahaan": {
                "id_perusahaan": "dd5b3f22-45d7-446f-95c7-907c5b8d4bb1",
                "id_desa": null,
                "nama_perusahaan": "CV Asia",
                "deskripsi_perusahaan": "Industri kemasan plastik",
                "alamat": "Jl. Rungkut Industri III/27A & 52, Surabaya 60293",
                "logo": "https://wlkp-assets.kemnaker.go.id/companies/dd5b3f22-45d7-446f-95c7-907c5b8d4bb1/61adb873b5587.png",
                "banner": "https://wlkp-assets.kemnaker.go.id/companies/dd5b3f22-45d7-446f-95c7-907c5b8d4bb1/61adb87f51b42.png",
                "created_at": "2025-10-10 16:42:57",
                "updated_at": "2025-10-29 14:58:15",
                "kode_kabupaten": "3578",
                "nama_kabupaten": "KOTA SURABAYA",
                "kode_provinsi": "35",
                "nama_provinsi": "JAWA TIMUR"
            },
            "jadwal": {
                "id_jadwal": "48039861-1251-474e-86af-d904e829093b",
                "angkatan": "2",
                "tanggal_batas_pendaftaran": "2025-10-03 00:00:00",
                "tanggal_mulai": "2025-11-24 00:00:00",
                "tanggal_selesai": "2026-05-23 23:59:59",
                "tahun": "2025",
                "tanggal_rencana_mulai": "2025-10-24 00:00:00",
                "tanggal_rencana_akhir": "2025-11-11 23:59:59",
                "tanggal_seleksi_mulai": "2025-11-12 00:00:00",
                "tanggal_seleksi_akhir": "2025-11-20 23:59:59",
                "tanggal_usulan_mulai": "2025-10-01 00:00:00",
                "tanggal_usulan_akhir": "2025-10-08 00:00:00",
                "tanggal_persetujuan_awal": "2025-10-05 00:00:00",
                "tanggal_persetujuan_akhir": "2025-10-06 00:00:00",
                "tanggal_pendaftaran_awal": "2025-11-06 00:00:00",
                "tanggal_pendaftaran_akhir": "2025-11-14 23:59:59",
                "tanggal_pengumuman_mulai": "2025-11-14 00:00:00",
                "tanggal_pengumuman_akhir": "2025-11-20 23:59:59",
                "tanggal_lulus_awal": "2024-11-01 00:00:00",
                "tanggal_lulus_akhir": "2025-10-31 00:00:00",
                "publish": 1
            },
            "government_agency": {
                "government_agency_name": null
            },
            "sub_government_agency": {
                "sub_government_agency_name": null
            }
        },
        {
            "id_posisi": "a04896f8-3572-4760-9f85-2da9c1e4e7b7",
            "posisi": "Magang Biro Umum (Bagian Tata  Usaha - TU Wakil  Menteri/Wakil Kepala  Badan)",
            "deskripsi_posisi": "Membantu melaksanakan urusan tata usaha pimpinan, keprotokolan, dan penyiapan bahan rapat pimpinan di lingkungan Kementerian Ekonomi Kreatif/Badan Ekonomi Kreatif",
            "syarat_khusus": null,
            "usia_minimal": null,
            "usia_maksimal": null,
            "revisi": null,
            "id_kondisi_fisik": null,
            "id_program": "f61110aa-46ac-4551-8789-08709fc46ab2",
            "created_at": "2025-11-05 14:38:34",
            "updated_at": "2025-11-05 14:38:34",
            "kode_kbji": null,
            "penempatan": null,
            "id_jenis_kelamin": null,
            "id_status_posisi": 2,
            "jumlah_kuota": 1,
            "jumlah_terdaftar": 4,
            "program_studi": "[{\"id\":\"b725ac52-6009-47c6-a349-3c15a8dc9141\",\"title\":\"Ilmu Politik\"},{\"id\":\"681a6e41-f24c-464d-838c-480fdef72f66\",\"title\":\"Sosiologi\"},{\"id\":\"95dd752e-e00f-4431-90bf-58bdd324a48f\",\"title\":\"Ilmu Komunikasi\"},{\"id\":\"d76ee81d-f5ec-4f98-beec-3c4c0c20a642\",\"title\":\"hubungan Internasional\"}]",
            "jenjang": "[\"Sarjana\"]",
            "ref_status_posisi": {
                "id_status_posisi": 2,
                "nama_status_posisi": "Terverifikasi"
            },
            "program": {
                "id_program": "f61110aa-46ac-4551-8789-08709fc46ab2",
                "id_sumber_dana": null,
                "id_perusahaan": "77c3d9a7-facb-4000-9d8f-92827eadeccd",
                "id_jadwal": "48039861-1251-474e-86af-d904e829093b"
            },
            "perusahaan": {
                "id_perusahaan": "77c3d9a7-facb-4000-9d8f-92827eadeccd",
                "id_desa": null,
                "nama_perusahaan": "Sekretariat Kementerian/ Sekretariat Utama",
                "deskripsi_perusahaan": null,
                "alamat": "Autograph Tower Lantai 33 Kompleks Thamrin Nine Jalan M.H. Thamrin No. 10, Jakarta Pusat 10230",
                "logo": "https://maganghub.kemnaker.go.id/be/v1/storage/uploads/logo/2025/11/pLfvYtMrP9ll60IdJY0u3qm0EP4KQ6TLCmbiP9gz.png",
                "banner": null,
                "created_at": "2025-11-05 14:38:34",
                "updated_at": "2025-11-05 14:38:34",
                "kode_kabupaten": "3171",
                "nama_kabupaten": "KOTA ADM. JAKARTA PUSAT",
                "kode_provinsi": "31",
                "nama_provinsi": "DKI JAKARTA"
            },
            "jadwal": {
                "id_jadwal": "48039861-1251-474e-86af-d904e829093b",
                "angkatan": "2",
                "tanggal_batas_pendaftaran": "2025-10-03 00:00:00",
                "tanggal_mulai": "2025-11-24 00:00:00",
                "tanggal_selesai": "2026-05-23 23:59:59",
                "tahun": "2025",
                "tanggal_rencana_mulai": "2025-10-24 00:00:00",
                "tanggal_rencana_akhir": "2025-11-11 23:59:59",
                "tanggal_seleksi_mulai": "2025-11-12 00:00:00",
                "tanggal_seleksi_akhir": "2025-11-20 23:59:59",
                "tanggal_usulan_mulai": "2025-10-01 00:00:00",
                "tanggal_usulan_akhir": "2025-10-08 00:00:00",
                "tanggal_persetujuan_awal": "2025-10-05 00:00:00",
                "tanggal_persetujuan_akhir": "2025-10-06 00:00:00",
                "tanggal_pendaftaran_awal": "2025-11-06 00:00:00",
                "tanggal_pendaftaran_akhir": "2025-11-14 23:59:59",
                "tanggal_pengumuman_mulai": "2025-11-14 00:00:00",
                "tanggal_pengumuman_akhir": "2025-11-20 23:59:59",
                "tanggal_lulus_awal": "2024-11-01 00:00:00",
                "tanggal_lulus_akhir": "2025-10-31 00:00:00",
                "publish": 1
            },
            "government_agency": {
                "government_agency_name": "Kementerian Ekonomi Kreatif"
            },
            "sub_government_agency": {
                "sub_government_agency_name": "Sekretariat Kementerian/ Sekretariat Utama"
            }
        },
        {
            "id_posisi": "a04896fd-7d56-4d96-92d6-b448358907f6",
            "posisi": "Magang Div. Teknologi -  Departemen Teknologi Produksi-Bagian Teknologi Proses",
            "deskripsi_posisi": "Bagian Teknologi Proses:\nMembantu Menjalankan kegiatan di Bagian Teknologi Proses yang meliputi kegiatan pengawasan standar proses produksi, pembuatan dokumen pendukung produksi (flowchart, flow process, detail takt system, process instruction, preparation table, painting procedure specification, bonding procedure specification, glass fiber reinforced plastic procedure specification, wiring connection procedure specification, cutting harness, dan Bill of Material consumable), analisa dan evaluasi permasalahan serta alternatif solusi terkait dengan proses produksi.",
            "syarat_khusus": null,
            "usia_minimal": null,
            "usia_maksimal": null,
            "revisi": null,
            "id_kondisi_fisik": null,
            "id_program": "69015474-2b15-41a2-b3b0-fdebab644733",
            "created_at": "2025-10-10 08:53:52",
            "updated_at": "2025-10-29 08:15:24",
            "kode_kbji": null,
            "penempatan": null,
            "id_jenis_kelamin": null,
            "id_status_posisi": 2,
            "jumlah_kuota": 1,
            "jumlah_terdaftar": 1,
            "program_studi": "[{\"id\":\"21442969-5763-4416-bb8d-56a80e55ada9\",\"title\":\"Teknik Mesin\"}]",
            "jenjang": "[\"Diploma\",\"Sarjana\"]",
            "ref_status_posisi": {
                "id_status_posisi": 2,
                "nama_status_posisi": "Terverifikasi"
            },
            "program": {
                "id_program": "69015474-2b15-41a2-b3b0-fdebab644733",
                "id_sumber_dana": null,
                "id_perusahaan": "06a78f24-4675-46e1-bb56-20efb6461a5e",
                "id_jadwal": "48039861-1251-474e-86af-d904e829093b"
            },
            "perusahaan": {
                "id_perusahaan": "06a78f24-4675-46e1-bb56-20efb6461a5e",
                "id_desa": null,
                "nama_perusahaan": "Perusahaan Perseroan (Persero) PT Industri Kereta Api",
                "deskripsi_perusahaan": "PT Industri Kereta Api atau PT INKA (Persero) merupakan Badan Usaha Milik Negara (BUMN) manufaktur kereta api terintegrasi pertama di Asia Tenggara. Fokus kami adalah menghasilkan produk dan jasa yang berkualitas tinggi bagi pelanggan. Kami menyediakan berbagai macam produk untuk memenuhi kebutuhan pelanggan serta after sales untuk memastikan bahwa pelanggan menerima produksi dengan kualitas terbaik. Produk kami telah diekspor ke berbagai negara, seperti Bangladesh, Filipina, Malaysia, Thailand, Singapura, dan Australia.",
                "alamat": "Jalan Yos Sudarso No. 71 Madiun\nJawa Timur",
                "logo": "https://wlkp-assets.kemnaker.go.id/companies/06a78f24-4675-46e1-bb56-20efb6461a5e/635b8a9b6b46e.png",
                "banner": "https://wlkp-assets.kemnaker.go.id/companies/06a78f24-4675-46e1-bb56-20efb6461a5e/614af7f83339c.jpg",
                "created_at": "2025-10-10 08:53:52",
                "updated_at": "2025-10-29 08:15:24",
                "kode_kabupaten": "3577",
                "nama_kabupaten": "KOTA MADIUN",
                "kode_provinsi": "35",
                "nama_provinsi": "JAWA TIMUR"
            },
            "jadwal": {
                "id_jadwal": "48039861-1251-474e-86af-d904e829093b",
                "angkatan": "2",
                "tanggal_batas_pendaftaran": "2025-10-03 00:00:00",
                "tanggal_mulai": "2025-11-24 00:00:00",
                "tanggal_selesai": "2026-05-23 23:59:59",
                "tahun": "2025",
                "tanggal_rencana_mulai": "2025-10-24 00:00:00",
                "tanggal_rencana_akhir": "2025-11-11 23:59:59",
                "tanggal_seleksi_mulai": "2025-11-12 00:00:00",
                "tanggal_seleksi_akhir": "2025-11-20 23:59:59",
                "tanggal_usulan_mulai": "2025-10-01 00:00:00",
                "tanggal_usulan_akhir": "2025-10-08 00:00:00",
                "tanggal_persetujuan_awal": "2025-10-05 00:00:00",
                "tanggal_persetujuan_akhir": "2025-10-06 00:00:00",
                "tanggal_pendaftaran_awal": "2025-11-06 00:00:00",
                "tanggal_pendaftaran_akhir": "2025-11-14 23:59:59",
                "tanggal_pengumuman_mulai": "2025-11-14 00:00:00",
                "tanggal_pengumuman_akhir": "2025-11-20 23:59:59",
                "tanggal_lulus_awal": "2024-11-01 00:00:00",
                "tanggal_lulus_akhir": "2025-10-31 00:00:00",
                "publish": 1
            },
            "government_agency": {
                "government_agency_name": null
            },
            "sub_government_agency": {
                "sub_government_agency_name": null
            }
        },
        {
            "id_posisi": "a04896fd-ecad-4239-b56f-a8a83fbb705f",
            "posisi": "Branch Business Development Intern",
            "deskripsi_posisi": "Deskripsi : \nBertanggung jawab untuk mendukung pencapaian bisnis cabang Bank Mandiri dengan melakukan mapping dan eksekusi potensi bisnis di wilayah sekitar Cabang sesuai strategi Bank. \n\nTugas & Tanggung Jawab: \n•\tMeningkatan ekosistem digital Bank Mandiri melalui edukasi dan pemasaran digital transaction product, seperti Livin', Kopra, Livin' Merchant, dan EDC Bank Mandiri\n•\tMendukung peningkatkan CASA (Current Account & Saving Account) baik dari nasabah eksisting maupun nasabah new to Bank\n•\tMendukung pertumbuhan ekonomi pada sektor usaha kecil dan menengah melalui referal kredit mikro\n•\tMendukung peningkatan akses layanan keuangan masyarakat melalui kegiatan promosi dan akuisisi Produk Bank\n•\tMendukung kegiatan operasional cabang terkait dengan administrasi, dokumentasi dan pengarsipan\n•\tMenjaga kerahasiaan data nasabah dan informasi Bank sesuai dengan kode etik dan regulasi \n\nKriteria:\n•\t⁠WNI\n•\t⁠Fresh graduate atau satu tahun setelah lulus\n•\t⁠S1 dari reputable university min. Akreditasi A/Unggul\n•\t⁠S1 min. IPK 3,00 dan S2 min. IPK 3,25\n•\t⁠S1 usia max. 24 dan S2 usia max. 26",
            "syarat_khusus": null,
            "usia_minimal": null,
            "usia_maksimal": null,
            "revisi": null,
            "id_kondisi_fisik": null,
            "id_program": "020f2e11-2370-4023-b9d0-11cb5d5566a7",
            "created_at": "2025-11-05 16:47:53",
            "updated_at": "2025-11-05 16:50:16",
            "kode_kbji": null,
            "penempatan": null,
            "id_jenis_kelamin": null,
            "id_status_posisi": 2,
            "jumlah_kuota": 1,
            "jumlah_terdaftar": 0,
            "program_studi": "[{\"id\":\"2fee5a6d-a685-4a85-911b-5aa7e4980851\",\"title\":\"Teknik Industri\"},{\"id\":\"95dd752e-e00f-4431-90bf-58bdd324a48f\",\"title\":\"Ilmu Komunikasi\"},{\"id\":\"c13ae920-a48f-4a7c-8c89-2b286a7fc225\",\"title\":\"Akuntansi\"},{\"id\":\"702dfd8b-b5b8-40fb-843b-4d503451b314\",\"title\":\"Ekonomi\"},{\"id\":\"a86f123a-2b95-4d24-b49d-174d3a639d91\",\"title\":\"Statistika\"}]",
            "jenjang": "[\"Sarjana\"]",
            "ref_status_posisi": {
                "id_status_posisi": 2,
                "nama_status_posisi": "Terverifikasi"
            },
            "program": {
                "id_program": "020f2e11-2370-4023-b9d0-11cb5d5566a7",
                "id_sumber_dana": null,
                "id_perusahaan": "9432cc6f-03c9-473b-b6a4-22ba2f1e8f10",
                "id_jadwal": "48039861-1251-474e-86af-d904e829093b"
            },
            "perusahaan": {
                "id_perusahaan": "9432cc6f-03c9-473b-b6a4-22ba2f1e8f10",
                "id_desa": null,
                "nama_perusahaan": "PT Perusahaan Perseroan (Persero) PT Bank Mandiri Tbk. Cabang Jakarta Departemen Hankam",
                "deskripsi_perusahaan": null,
                "alamat": "Jl. Medan Merdeka Barat 13 -14 \nJakarta Pusat",
                "logo": "https://wlkp-assets.kemnaker.go.id/companies/19dee605-5f7a-44ca-9b17-c27ab08e6e9d/5fab686448b21.jpeg",
                "banner": "https://wlkp-assets.kemnaker.go.id/companies/19dee605-5f7a-44ca-9b17-c27ab08e6e9d/5fab6472b0d42.jpg",
                "created_at": "2025-11-05 16:47:53",
                "updated_at": "2025-11-05 16:50:16",
                "kode_kabupaten": "3171",
                "nama_kabupaten": "KOTA ADM. JAKARTA PUSAT",
                "kode_provinsi": "31",
                "nama_provinsi": "DKI JAKARTA"
            },
            "jadwal": {
                "id_jadwal": "48039861-1251-474e-86af-d904e829093b",
                "angkatan": "2",
                "tanggal_batas_pendaftaran": "2025-10-03 00:00:00",
                "tanggal_mulai": "2025-11-24 00:00:00",
                "tanggal_selesai": "2026-05-23 23:59:59",
                "tahun": "2025",
                "tanggal_rencana_mulai": "2025-10-24 00:00:00",
                "tanggal_rencana_akhir": "2025-11-11 23:59:59",
                "tanggal_seleksi_mulai": "2025-11-12 00:00:00",
                "tanggal_seleksi_akhir": "2025-11-20 23:59:59",
                "tanggal_usulan_mulai": "2025-10-01 00:00:00",
                "tanggal_usulan_akhir": "2025-10-08 00:00:00",
                "tanggal_persetujuan_awal": "2025-10-05 00:00:00",
                "tanggal_persetujuan_akhir": "2025-10-06 00:00:00",
                "tanggal_pendaftaran_awal": "2025-11-06 00:00:00",
                "tanggal_pendaftaran_akhir": "2025-11-14 23:59:59",
                "tanggal_pengumuman_mulai": "2025-11-14 00:00:00",
                "tanggal_pengumuman_akhir": "2025-11-20 23:59:59",
                "tanggal_lulus_awal": "2024-11-01 00:00:00",
                "tanggal_lulus_akhir": "2025-10-31 00:00:00",
                "publish": 1
            },
            "government_agency": {
                "government_agency_name": null
            },
            "sub_government_agency": {
                "sub_government_agency_name": null
            }
        },
        {
            "id_posisi": "a0489725-dde5-4d3a-aee4-b21b6ec3e64a",
            "posisi": "Arsiparis",
            "deskripsi_posisi": "1. Pengumpulan dan Pengolahan Arsip: Mengumpulkan, mengolah, dan mengelola arsip yang dihasilkan oleh instansi.\n2. Pengklasifikasian dan Pengindeksan: Mengklasifikasikan dan mengindeks arsip berdasarkan sistem klasifikasi yang berlaku.\n3. Penyimpanan dan Pemeliharaan: Menyimpan dan memelihara arsip dalam kondisi yang baik dan aman.\n4. Pencarian dan Pengeluaran: Mencari dan mengeluarkan arsip yang dibutuhkan oleh instansi.\n5. Pengawasan dan Pengendalian: Mengawasi dan mengendalikan arus arsip masuk dan keluar.",
            "syarat_khusus": null,
            "usia_minimal": null,
            "usia_maksimal": null,
            "revisi": null,
            "id_kondisi_fisik": null,
            "id_program": "b3507d55-7320-4ecf-8e9a-d3fd5eeebe37",
            "created_at": "2025-11-05 16:09:12",
            "updated_at": "2025-11-05 16:09:12",
            "kode_kbji": null,
            "penempatan": null,
            "id_jenis_kelamin": null,
            "id_status_posisi": 2,
            "jumlah_kuota": 1,
            "jumlah_terdaftar": 11,
            "program_studi": "[{\"id\":\"2c88d9da-5636-40d2-9d1d-d3882c313960\",\"title\":\"Kearsipan\"},{\"id\":\"4974b683-cf42-4cf0-a6df-856f69e2df68\",\"title\":\"Manajemen Rekod dan Arsip\"},{\"id\":\"8860e036-9ae0-422c-8883-148e8c563259\",\"title\":\"Pengelolaan Arsip dan Rekaman Informasi\"},{\"id\":\"5ddbf6de-a65b-4385-bc0a-267c5539e52d\",\"title\":\"Kearsipan Digital\"}]",
            "jenjang": "[\"Sarjana\",\"Diploma\"]",
            "ref_status_posisi": {
                "id_status_posisi": 2,
                "nama_status_posisi": "Terverifikasi"
            },
            "program": {
                "id_program": "b3507d55-7320-4ecf-8e9a-d3fd5eeebe37",
                "id_sumber_dana": null,
                "id_perusahaan": "60403e9c-97d5-4f43-ae32-ef4570cdb3f3",
                "id_jadwal": "48039861-1251-474e-86af-d904e829093b"
            },
            "perusahaan": {
                "id_perusahaan": "60403e9c-97d5-4f43-ae32-ef4570cdb3f3",
                "id_desa": null,
                "nama_perusahaan": "Balai POM di Bau-Bau",
                "deskripsi_perusahaan": null,
                "alamat": "Jl. Bakti Abri Bukit Wolio Indah, Baubau",
                "logo": "https://maganghub.kemnaker.go.id/be/v1/storage/uploads/logo/2025/11/jlnFsrLJxOaPpaQ6IkOSVZQeSKnzqq8X97RVlsxV.png",
                "banner": null,
                "created_at": "2025-11-05 16:09:12",
                "updated_at": "2025-11-05 16:09:12",
                "kode_kabupaten": "7472",
                "nama_kabupaten": "KOTA BAU BAU",
                "kode_provinsi": "74",
                "nama_provinsi": "SULAWESI TENGGARA"
            },
            "jadwal": {
                "id_jadwal": "48039861-1251-474e-86af-d904e829093b",
                "angkatan": "2",
                "tanggal_batas_pendaftaran": "2025-10-03 00:00:00",
                "tanggal_mulai": "2025-11-24 00:00:00",
                "tanggal_selesai": "2026-05-23 23:59:59",
                "tahun": "2025",
                "tanggal_rencana_mulai": "2025-10-24 00:00:00",
                "tanggal_rencana_akhir": "2025-11-11 23:59:59",
                "tanggal_seleksi_mulai": "2025-11-12 00:00:00",
                "tanggal_seleksi_akhir": "2025-11-20 23:59:59",
                "tanggal_usulan_mulai": "2025-10-01 00:00:00",
                "tanggal_usulan_akhir": "2025-10-08 00:00:00",
                "tanggal_persetujuan_awal": "2025-10-05 00:00:00",
                "tanggal_persetujuan_akhir": "2025-10-06 00:00:00",
                "tanggal_pendaftaran_awal": "2025-11-06 00:00:00",
                "tanggal_pendaftaran_akhir": "2025-11-14 23:59:59",
                "tanggal_pengumuman_mulai": "2025-11-14 00:00:00",
                "tanggal_pengumuman_akhir": "2025-11-20 23:59:59",
                "tanggal_lulus_awal": "2024-11-01 00:00:00",
                "tanggal_lulus_akhir": "2025-10-31 00:00:00",
                "publish": 1
            },
            "government_agency": {
                "government_agency_name": "Badan Pengawas Obat dan Makanan"
            },
            "sub_government_agency": {
                "sub_government_agency_name": "Balai POM di Bau-Bau"
            }
        },
        {
            "id_posisi": "a0489743-3ae0-4a70-b114-9bb13d53b9e1",
            "posisi": "Health, Safety and Environment Intern",
            "deskripsi_posisi": "1. Terlibat dalam melakukan inspeksi keselamatan kerja di area operasional.\n2. Terlibat dalam mengidentifikasi potensi bahaya dan penilaian risiko kerja.\n3. Membantu memastikan penggunaan APD (Alat Pelindung Diri) sesuai dengan standar perusahaan.\n4. Terlibat dalam pembaruan dokumen HSE seperti SOP, JSA, HIRARC dan Form Inspeksi.\n5. Berkoordinasi dengan tim operasional untuk memastikan kepatuhan terhadap prosedur K3 dan lingkungan.",
            "syarat_khusus": null,
            "usia_minimal": null,
            "usia_maksimal": null,
            "revisi": null,
            "id_kondisi_fisik": null,
            "id_program": "8205d9b1-a918-42ab-aaf8-2b2a27d80e1f",
            "created_at": "2025-11-04 16:15:24",
            "updated_at": "2025-11-04 16:39:55",
            "kode_kbji": null,
            "penempatan": null,
            "id_jenis_kelamin": null,
            "id_status_posisi": 2,
            "jumlah_kuota": 1,
            "jumlah_terdaftar": 7,
            "program_studi": "[{\"id\":\"03fa0c8f-47f8-4042-951a-a08e48aea3ac\",\"title\":\"Teknik Lingkungan\"},{\"id\":\"4d4d12e0-fd86-4c3c-9e11-3b8b50ba383c\",\"title\":\"Higiene Perusahaan Kesehatan dan Keselamatan Kerja\"},{\"id\":\"4771fc3c-907f-4b0b-adde-ef9b4434425d\",\"title\":\"Ilmu Kesehatan Masyarakat\"},{\"id\":\"9bb9f909-f27d-4d53-9611-e17ed549a5ac\",\"title\":\"Kesehatan Lingkungan\"}]",
            "jenjang": "[\"Diploma\",\"Sarjana\"]",
            "ref_status_posisi": {
                "id_status_posisi": 2,
                "nama_status_posisi": "Terverifikasi"
            },
            "program": {
                "id_program": "8205d9b1-a918-42ab-aaf8-2b2a27d80e1f",
                "id_sumber_dana": null,
                "id_perusahaan": "44539f8f-e026-4906-8199-362df25114dd",
                "id_jadwal": "48039861-1251-474e-86af-d904e829093b"
            },
            "perusahaan": {
                "id_perusahaan": "44539f8f-e026-4906-8199-362df25114dd",
                "id_desa": null,
                "nama_perusahaan": "Wasteforchange Alam Indonesia",
                "deskripsi_perusahaan": null,
                "alamat": "Kantor Waste4Change Vida Bumipala, Jl. Alun Alun Utara, RT.002/RW.001, Padurenan, Kec. Mustika Jaya, Kota Bks, Jawa Barat",
                "logo": "https://wlkp-assets.kemnaker.go.id/companies/5b81732c-5ff2-4301-8f60-7451c499fc61/61b1760b5977e.jpg",
                "banner": "https://wlkp-assets.kemnaker.go.id/companies/5b81732c-5ff2-4301-8f60-7451c499fc61/61b1762565b16.jfif",
                "created_at": "2025-11-04 16:15:24",
                "updated_at": "2025-11-04 16:39:55",
                "kode_kabupaten": "3275",
                "nama_kabupaten": "KOTA BEKASI",
                "kode_provinsi": "32",
                "nama_provinsi": "JAWA BARAT"
            },
            "jadwal": {
                "id_jadwal": "48039861-1251-474e-86af-d904e829093b",
                "angkatan": "2",
                "tanggal_batas_pendaftaran": "2025-10-03 00:00:00",
                "tanggal_mulai": "2025-11-24 00:00:00",
                "tanggal_selesai": "2026-05-23 23:59:59",
                "tahun": "2025",
                "tanggal_rencana_mulai": "2025-10-24 00:00:00",
                "tanggal_rencana_akhir": "2025-11-11 23:59:59",
                "tanggal_seleksi_mulai": "2025-11-12 00:00:00",
                "tanggal_seleksi_akhir": "2025-11-20 23:59:59",
                "tanggal_usulan_mulai": "2025-10-01 00:00:00",
                "tanggal_usulan_akhir": "2025-10-08 00:00:00",
                "tanggal_persetujuan_awal": "2025-10-05 00:00:00",
                "tanggal_persetujuan_akhir": "2025-10-06 00:00:00",
                "tanggal_pendaftaran_awal": "2025-11-06 00:00:00",
                "tanggal_pendaftaran_akhir": "2025-11-14 23:59:59",
                "tanggal_pengumuman_mulai": "2025-11-14 00:00:00",
                "tanggal_pengumuman_akhir": "2025-11-20 23:59:59",
                "tanggal_lulus_awal": "2024-11-01 00:00:00",
                "tanggal_lulus_akhir": "2025-10-31 00:00:00",
                "publish": 1
            },
            "government_agency": {
                "government_agency_name": null
            },
            "sub_government_agency": {
                "sub_government_agency_name": null
            }
        },
        {
            "id_posisi": "a0489757-a541-4ed1-a6be-2d628e608a90",
            "posisi": "Field Officer / Penyuluh Lapangan Porang",
            "deskripsi_posisi": "Melakukan pembinaan kepada petani mengenai teknik penanaman, pemupukan, dan panen.\nMengkoordinasikan kegiatan monitoring lahan dan hasil produksi.\nMenjadi penghubung antara perusahaan dan kelompok tani.",
            "syarat_khusus": null,
            "usia_minimal": null,
            "usia_maksimal": null,
            "revisi": null,
            "id_kondisi_fisik": null,
            "id_program": "e0a30673-2b25-4e4f-b38b-4ebc7c8785c1",
            "created_at": "2025-11-04 12:47:59",
            "updated_at": "2025-11-04 13:19:34",
            "kode_kbji": null,
            "penempatan": null,
            "id_jenis_kelamin": null,
            "id_status_posisi": 2,
            "jumlah_kuota": 1,
            "jumlah_terdaftar": 3,
            "program_studi": "[{\"id\":\"1f660005-1210-4980-8a17-c7084d1f49ea\",\"title\":\"Agroteknologi\"}]",
            "jenjang": "[\"Sarjana\"]",
            "ref_status_posisi": {
                "id_status_posisi": 2,
                "nama_status_posisi": "Terverifikasi"
            },
            "program": {
                "id_program": "e0a30673-2b25-4e4f-b38b-4ebc7c8785c1",
                "id_sumber_dana": null,
                "id_perusahaan": "64cb3b8e-f344-4b38-a010-2353dca4636b",
                "id_jadwal": "48039861-1251-474e-86af-d904e829093b"
            },
            "perusahaan": {
                "id_perusahaan": "64cb3b8e-f344-4b38-a010-2353dca4636b",
                "id_desa": null,
                "nama_perusahaan": "Alfatih Porang Indonesia",
                "deskripsi_perusahaan": null,
                "alamat": "Kec wattang sidendreng",
                "logo": null,
                "banner": null,
                "created_at": "2025-11-04 12:47:59",
                "updated_at": "2025-11-04 13:19:34",
                "kode_kabupaten": "7314",
                "nama_kabupaten": "KAB. SIDENRENG RAPPANG",
                "kode_provinsi": "73",
                "nama_provinsi": "SULAWESI SELATAN"
            },
            "jadwal": {
                "id_jadwal": "48039861-1251-474e-86af-d904e829093b",
                "angkatan": "2",
                "tanggal_batas_pendaftaran": "2025-10-03 00:00:00",
                "tanggal_mulai": "2025-11-24 00:00:00",
                "tanggal_selesai": "2026-05-23 23:59:59",
                "tahun": "2025",
                "tanggal_rencana_mulai": "2025-10-24 00:00:00",
                "tanggal_rencana_akhir": "2025-11-11 23:59:59",
                "tanggal_seleksi_mulai": "2025-11-12 00:00:00",
                "tanggal_seleksi_akhir": "2025-11-20 23:59:59",
                "tanggal_usulan_mulai": "2025-10-01 00:00:00",
                "tanggal_usulan_akhir": "2025-10-08 00:00:00",
                "tanggal_persetujuan_awal": "2025-10-05 00:00:00",
                "tanggal_persetujuan_akhir": "2025-10-06 00:00:00",
                "tanggal_pendaftaran_awal": "2025-11-06 00:00:00",
                "tanggal_pendaftaran_akhir": "2025-11-14 23:59:59",
                "tanggal_pengumuman_mulai": "2025-11-14 00:00:00",
                "tanggal_pengumuman_akhir": "2025-11-20 23:59:59",
                "tanggal_lulus_awal": "2024-11-01 00:00:00",
                "tanggal_lulus_akhir": "2025-10-31 00:00:00",
                "publish": 1
            },
            "government_agency": {
                "government_agency_name": null
            },
            "sub_government_agency": {
                "sub_government_agency_name": null
            }
        },
        {
            "id_posisi": "a048975a-c2b1-4106-91fe-a5f7b5e5bb4e",
            "posisi": "Sales Representative",
            "deskripsi_posisi": "Nurture and strengthen relationships with our existing customers.\nOffer support and guidance by providing customized solutions to client needs.\nActively identify, approach, and engage with potential clients to grow our network.",
            "syarat_khusus": null,
            "usia_minimal": null,
            "usia_maksimal": null,
            "revisi": null,
            "id_kondisi_fisik": null,
            "id_program": "9f346e13-d4eb-43ab-8d89-75f75eac70c3",
            "created_at": "2025-11-03 20:26:47",
            "updated_at": "2025-11-05 09:49:55",
            "kode_kbji": null,
            "penempatan": null,
            "id_jenis_kelamin": null,
            "id_status_posisi": 2,
            "jumlah_kuota": 1,
            "jumlah_terdaftar": 1,
            "program_studi": "[{\"id\":\"2f6440b7-d057-40e7-bce1-9a4cf73f441d\",\"title\":\"Manajemen\"},{\"id\":\"702dfd8b-b5b8-40fb-843b-4d503451b314\",\"title\":\"Ekonomi\"},{\"id\":\"e12302ac-c8dc-4d0a-90a7-402f6fafd27e\",\"title\":\"Manajemen Pemasaran\\/Marketing\"},{\"id\":\"95dd752e-e00f-4431-90bf-58bdd324a48f\",\"title\":\"Ilmu Komunikasi\"},{\"id\":\"8631f68c-a0f0-4758-9251-a62190209909\",\"title\":\"Hubungan Masyarakat\"}]",
            "jenjang": "[\"Sarjana\"]",
            "ref_status_posisi": {
                "id_status_posisi": 2,
                "nama_status_posisi": "Terverifikasi"
            },
            "program": {
                "id_program": "9f346e13-d4eb-43ab-8d89-75f75eac70c3",
                "id_sumber_dana": null,
                "id_perusahaan": "52ad3b41-db03-4cd8-8c68-2c21680f467a",
                "id_jadwal": "48039861-1251-474e-86af-d904e829093b"
            },
            "perusahaan": {
                "id_perusahaan": "52ad3b41-db03-4cd8-8c68-2c21680f467a",
                "id_desa": null,
                "nama_perusahaan": "Pcba Semiconductor International",
                "deskripsi_perusahaan": null,
                "alamat": "Jodoh Permai Blok H No 18, Batam City, Riau Islands",
                "logo": "https://wlkp-assets.kemnaker.go.id/companies/982d1dc6-45ec-4f75-9adf-ac94014d54a8/6908805d97fee.png",
                "banner": "https://wlkp-assets.kemnaker.go.id/companies/982d1dc6-45ec-4f75-9adf-ac94014d54a8/690880617dafa.png",
                "created_at": "2025-11-03 20:26:47",
                "updated_at": "2025-11-05 09:49:55",
                "kode_kabupaten": "2171",
                "nama_kabupaten": "KOTA BATAM",
                "kode_provinsi": "21",
                "nama_provinsi": "KEPULAUAN RIAU"
            },
            "jadwal": {
                "id_jadwal": "48039861-1251-474e-86af-d904e829093b",
                "angkatan": "2",
                "tanggal_batas_pendaftaran": "2025-10-03 00:00:00",
                "tanggal_mulai": "2025-11-24 00:00:00",
                "tanggal_selesai": "2026-05-23 23:59:59",
                "tahun": "2025",
                "tanggal_rencana_mulai": "2025-10-24 00:00:00",
                "tanggal_rencana_akhir": "2025-11-11 23:59:59",
                "tanggal_seleksi_mulai": "2025-11-12 00:00:00",
                "tanggal_seleksi_akhir": "2025-11-20 23:59:59",
                "tanggal_usulan_mulai": "2025-10-01 00:00:00",
                "tanggal_usulan_akhir": "2025-10-08 00:00:00",
                "tanggal_persetujuan_awal": "2025-10-05 00:00:00",
                "tanggal_persetujuan_akhir": "2025-10-06 00:00:00",
                "tanggal_pendaftaran_awal": "2025-11-06 00:00:00",
                "tanggal_pendaftaran_akhir": "2025-11-14 23:59:59",
                "tanggal_pengumuman_mulai": "2025-11-14 00:00:00",
                "tanggal_pengumuman_akhir": "2025-11-20 23:59:59",
                "tanggal_lulus_awal": "2024-11-01 00:00:00",
                "tanggal_lulus_akhir": "2025-10-31 00:00:00",
                "publish": 1
            },
            "government_agency": {
                "government_agency_name": null
            },
            "sub_government_agency": {
                "sub_government_agency_name": null
            }
        },
        {
            "id_posisi": "a048975d-e58d-4d28-bb2d-8069389c395d",
            "posisi": "Vendor Management Intern",
            "deskripsi_posisi": "Mendukung proses vendor management dengan melakukan kualifikasi dan evaluasi terhadap calon vendor yang akan menjadi rekanan Auto2000, guna memastikan kesesuaian dengan standar dan kebutuhan perusahaan.",
            "syarat_khusus": null,
            "usia_minimal": null,
            "usia_maksimal": null,
            "revisi": null,
            "id_kondisi_fisik": null,
            "id_program": "91d2e717-7cda-4bb9-b405-e232fe2d0ffd",
            "created_at": "2025-10-10 07:55:19",
            "updated_at": "2025-11-03 16:35:35",
            "kode_kbji": null,
            "penempatan": null,
            "id_jenis_kelamin": null,
            "id_status_posisi": 2,
            "jumlah_kuota": 1,
            "jumlah_terdaftar": 2,
            "program_studi": "[{\"id\":\"0f2300cb-4d1e-4059-907c-b8377df8d514\",\"title\":\"Keuangan\"},{\"id\":\"c13ae920-a48f-4a7c-8c89-2b286a7fc225\",\"title\":\"Akuntansi\"},{\"id\":\"2fee5a6d-a685-4a85-911b-5aa7e4980851\",\"title\":\"Teknik Industri\"}]",
            "jenjang": "[\"Sarjana\"]",
            "ref_status_posisi": {
                "id_status_posisi": 2,
                "nama_status_posisi": "Terverifikasi"
            },
            "program": {
                "id_program": "91d2e717-7cda-4bb9-b405-e232fe2d0ffd",
                "id_sumber_dana": null,
                "id_perusahaan": "4b511c18-2e10-434c-8081-eaaf7bbe2e3f",
                "id_jadwal": "48039861-1251-474e-86af-d904e829093b"
            },
            "perusahaan": {
                "id_perusahaan": "4b511c18-2e10-434c-8081-eaaf7bbe2e3f",
                "id_desa": null,
                "nama_perusahaan": "PT. Astra International Tbk - Toyota Sales Operation",
                "deskripsi_perusahaan": null,
                "alamat": "Menara Astra Lt. 58-63, Jalan Jendral Sudirman Kav 5-6, Jakarta 10220",
                "logo": null,
                "banner": null,
                "created_at": "2025-10-10 07:55:19",
                "updated_at": "2025-11-03 16:35:35",
                "kode_kabupaten": "3171",
                "nama_kabupaten": "KOTA ADM. JAKARTA PUSAT",
                "kode_provinsi": "31",
                "nama_provinsi": "DKI JAKARTA"
            },
            "jadwal": {
                "id_jadwal": "48039861-1251-474e-86af-d904e829093b",
                "angkatan": "2",
                "tanggal_batas_pendaftaran": "2025-10-03 00:00:00",
                "tanggal_mulai": "2025-11-24 00:00:00",
                "tanggal_selesai": "2026-05-23 23:59:59",
                "tahun": "2025",
                "tanggal_rencana_mulai": "2025-10-24 00:00:00",
                "tanggal_rencana_akhir": "2025-11-11 23:59:59",
                "tanggal_seleksi_mulai": "2025-11-12 00:00:00",
                "tanggal_seleksi_akhir": "2025-11-20 23:59:59",
                "tanggal_usulan_mulai": "2025-10-01 00:00:00",
                "tanggal_usulan_akhir": "2025-10-08 00:00:00",
                "tanggal_persetujuan_awal": "2025-10-05 00:00:00",
                "tanggal_persetujuan_akhir": "2025-10-06 00:00:00",
                "tanggal_pendaftaran_awal": "2025-11-06 00:00:00",
                "tanggal_pendaftaran_akhir": "2025-11-14 23:59:59",
                "tanggal_pengumuman_mulai": "2025-11-14 00:00:00",
                "tanggal_pengumuman_akhir": "2025-11-20 23:59:59",
                "tanggal_lulus_awal": "2024-11-01 00:00:00",
                "tanggal_lulus_akhir": "2025-10-31 00:00:00",
                "publish": 1
            },
            "government_agency": {
                "government_agency_name": null
            },
            "sub_government_agency": {
                "sub_government_agency_name": null
            }
        },
        {
            "id_posisi": "a048975e-cadc-45a3-a000-63aae3dbae68",
            "posisi": "Legal Intern",
            "deskripsi_posisi": "Job Description:\nWe are looking for a Legal Intern to support our Legal Department in various administrative and legal activities, covering corporate, commercial, and litigation matters. This role provides comprehensive exposure to different areas of legal practice and is ideal for fresh law graduates who are eager to learn and gain hands-on experience in a corporate legal environment.\n\nResponsibilities:\n- Assist in preparing and organizing legal documents, agreements, and correspondence.\n- Support corporate legal matters, including company documents, licenses, and compliance.\n- Help with commercial contract drafting, review, and filing.\n- Provide administrative support in litigation cases, including document compilation and coordination with external parties.\n- Conduct basic legal research and prepare summaries as requested.\n- Ensure proper filing and maintenance of legal archives.\n\nQualifications:\n- Fresh graduate from Law (S1 Hukum).\n- Basic understanding of corporate law, contract law, and litigation procedures.\n- Strong attention to detail and confidentiality in handling legal documents.\n- Proficient in Microsoft Office and administrative documentation.\n- Good analytical, communication, and teamwork skills.",
            "syarat_khusus": null,
            "usia_minimal": null,
            "usia_maksimal": null,
            "revisi": null,
            "id_kondisi_fisik": null,
            "id_program": "65e39d73-44e4-485f-8870-5bffe981782c",
            "created_at": "2025-11-04 10:36:24",
            "updated_at": "2025-11-05 17:43:44",
            "kode_kbji": null,
            "penempatan": null,
            "id_jenis_kelamin": null,
            "id_status_posisi": 2,
            "jumlah_kuota": 1,
            "jumlah_terdaftar": 6,
            "program_studi": "[{\"id\":\"fd3ebf70-4f4b-4dab-a7ab-ec31d20bd01b\",\"title\":\"Hukum\"},{\"id\":\"277d622d-242a-40a4-a46a-ee63cf22fc0a\",\"title\":\"Hukum Bisnis\"}]",
            "jenjang": "[\"Sarjana\"]",
            "ref_status_posisi": {
                "id_status_posisi": 2,
                "nama_status_posisi": "Terverifikasi"
            },
            "program": {
                "id_program": "65e39d73-44e4-485f-8870-5bffe981782c",
                "id_sumber_dana": null,
                "id_perusahaan": "ddcd3804-4f89-479f-80af-8d411edc7c66",
                "id_jadwal": "48039861-1251-474e-86af-d904e829093b"
            },
            "perusahaan": {
                "id_perusahaan": "ddcd3804-4f89-479f-80af-8d411edc7c66",
                "id_desa": null,
                "nama_perusahaan": "Hasana Damai Putra",
                "deskripsi_perusahaan": null,
                "alamat": "Kompleks Sentra Niaga, Bulevar Hijau Kav. 33 – 35",
                "logo": "https://wlkp-assets.kemnaker.go.id/companies/7a8f8f3b-cff2-4ca5-a424-c08db37d882a/690333a62e3ee.jpeg",
                "banner": "https://wlkp-assets.kemnaker.go.id/companies/7a8f8f3b-cff2-4ca5-a424-c08db37d882a/6903338b1a849.jpeg",
                "created_at": "2025-11-04 10:36:24",
                "updated_at": "2025-11-05 17:43:44",
                "kode_kabupaten": "3275",
                "nama_kabupaten": "KOTA BEKASI",
                "kode_provinsi": "32",
                "nama_provinsi": "JAWA BARAT"
            },
            "jadwal": {
                "id_jadwal": "48039861-1251-474e-86af-d904e829093b",
                "angkatan": "2",
                "tanggal_batas_pendaftaran": "2025-10-03 00:00:00",
                "tanggal_mulai": "2025-11-24 00:00:00",
                "tanggal_selesai": "2026-05-23 23:59:59",
                "tahun": "2025",
                "tanggal_rencana_mulai": "2025-10-24 00:00:00",
                "tanggal_rencana_akhir": "2025-11-11 23:59:59",
                "tanggal_seleksi_mulai": "2025-11-12 00:00:00",
                "tanggal_seleksi_akhir": "2025-11-20 23:59:59",
                "tanggal_usulan_mulai": "2025-10-01 00:00:00",
                "tanggal_usulan_akhir": "2025-10-08 00:00:00",
                "tanggal_persetujuan_awal": "2025-10-05 00:00:00",
                "tanggal_persetujuan_akhir": "2025-10-06 00:00:00",
                "tanggal_pendaftaran_awal": "2025-11-06 00:00:00",
                "tanggal_pendaftaran_akhir": "2025-11-14 23:59:59",
                "tanggal_pengumuman_mulai": "2025-11-14 00:00:00",
                "tanggal_pengumuman_akhir": "2025-11-20 23:59:59",
                "tanggal_lulus_awal": "2024-11-01 00:00:00",
                "tanggal_lulus_akhir": "2025-10-31 00:00:00",
                "publish": 1
            },
            "government_agency": {
                "government_agency_name": null
            },
            "sub_government_agency": {
                "sub_government_agency_name": null
            }
        },
        {
            "id_posisi": "a0489760-1a94-4473-9f1b-2f576c0c3580",
            "posisi": "Marketing Eksternal & Event Support Intern",
            "deskripsi_posisi": "Mendukung pelaksanaan kegiatan promosi lapangan, kunjungan komunitas, dan event korporasi. Melakukan pendataan serta pelaporan hasil kegiatan promosi eksternal.",
            "syarat_khusus": null,
            "usia_minimal": null,
            "usia_maksimal": null,
            "revisi": null,
            "id_kondisi_fisik": null,
            "id_program": "cc21ba28-f8b5-40d4-a136-2e0cdb1d77f7",
            "created_at": "2025-11-04 13:36:19",
            "updated_at": "2025-11-04 14:16:19",
            "kode_kbji": null,
            "penempatan": null,
            "id_jenis_kelamin": null,
            "id_status_posisi": 2,
            "jumlah_kuota": 1,
            "jumlah_terdaftar": 0,
            "program_studi": "[{\"id\":\"e12302ac-c8dc-4d0a-90a7-402f6fafd27e\",\"title\":\"Manajemen Pemasaran\\/Marketing\"},{\"id\":\"2f6440b7-d057-40e7-bce1-9a4cf73f441d\",\"title\":\"Manajemen\"},{\"id\":\"95dd752e-e00f-4431-90bf-58bdd324a48f\",\"title\":\"Ilmu Komunikasi\"},{\"id\":\"8631f68c-a0f0-4758-9251-a62190209909\",\"title\":\"Hubungan Masyarakat\"}]",
            "jenjang": "[\"Diploma\",\"Sarjana\"]",
            "ref_status_posisi": {
                "id_status_posisi": 2,
                "nama_status_posisi": "Terverifikasi"
            },
            "program": {
                "id_program": "cc21ba28-f8b5-40d4-a136-2e0cdb1d77f7",
                "id_sumber_dana": null,
                "id_perusahaan": "f776796a-89f1-4921-a95a-b5b0c5e0ce0a",
                "id_jadwal": "48039861-1251-474e-86af-d904e829093b"
            },
            "perusahaan": {
                "id_perusahaan": "f776796a-89f1-4921-a95a-b5b0c5e0ce0a",
                "id_desa": null,
                "nama_perusahaan": "Bentang Salapan Kahuripan",
                "deskripsi_perusahaan": null,
                "alamat": "Jl. Raya Bandung-Cianjur KM. 17, Bojong, \nKec. Karangtengah, Kabupaten Cianjur, Jawa Barat 43281",
                "logo": "https://wlkp-assets.kemnaker.go.id/companies/db84b140-a5a6-480a-aabb-fe3452f4af9c/6715edcd997bb.jpeg",
                "banner": "https://wlkp-assets.kemnaker.go.id/companies/db84b140-a5a6-480a-aabb-fe3452f4af9c/6715ee795b7a5.jpg",
                "created_at": "2025-11-04 13:36:19",
                "updated_at": "2025-11-04 14:16:19",
                "kode_kabupaten": "3203",
                "nama_kabupaten": "KAB. CIANJUR",
                "kode_provinsi": "32",
                "nama_provinsi": "JAWA BARAT"
            },
            "jadwal": {
                "id_jadwal": "48039861-1251-474e-86af-d904e829093b",
                "angkatan": "2",
                "tanggal_batas_pendaftaran": "2025-10-03 00:00:00",
                "tanggal_mulai": "2025-11-24 00:00:00",
                "tanggal_selesai": "2026-05-23 23:59:59",
                "tahun": "2025",
                "tanggal_rencana_mulai": "2025-10-24 00:00:00",
                "tanggal_rencana_akhir": "2025-11-11 23:59:59",
                "tanggal_seleksi_mulai": "2025-11-12 00:00:00",
                "tanggal_seleksi_akhir": "2025-11-20 23:59:59",
                "tanggal_usulan_mulai": "2025-10-01 00:00:00",
                "tanggal_usulan_akhir": "2025-10-08 00:00:00",
                "tanggal_persetujuan_awal": "2025-10-05 00:00:00",
                "tanggal_persetujuan_akhir": "2025-10-06 00:00:00",
                "tanggal_pendaftaran_awal": "2025-11-06 00:00:00",
                "tanggal_pendaftaran_akhir": "2025-11-14 23:59:59",
                "tanggal_pengumuman_mulai": "2025-11-14 00:00:00",
                "tanggal_pengumuman_akhir": "2025-11-20 23:59:59",
                "tanggal_lulus_awal": "2024-11-01 00:00:00",
                "tanggal_lulus_akhir": "2025-10-31 00:00:00",
                "publish": 1
            },
            "government_agency": {
                "government_agency_name": null
            },
            "sub_government_agency": {
                "sub_government_agency_name": null
            }
        },
        {
            "id_posisi": "a0489764-ab1f-472a-99a1-1c2b778d6026",
            "posisi": "Arsiparis",
            "deskripsi_posisi": "perancangan sistem kearsipan, pengolahan dan penyajian informasi, pembinaan tertib kearsipan, serta menjaga kerahasiaan dan keamanan arsip, baik dalam format fisik maupun digital",
            "syarat_khusus": null,
            "usia_minimal": null,
            "usia_maksimal": null,
            "revisi": null,
            "id_kondisi_fisik": null,
            "id_program": "847c168d-7c13-4fb4-97e6-8169c94ec775",
            "created_at": "2025-11-05 16:05:46",
            "updated_at": "2025-11-05 16:05:46",
            "kode_kbji": null,
            "penempatan": null,
            "id_jenis_kelamin": null,
            "id_status_posisi": 2,
            "jumlah_kuota": 1,
            "jumlah_terdaftar": 2,
            "program_studi": "[{\"id\":\"2c88d9da-5636-40d2-9d1d-d3882c313960\",\"title\":\"Kearsipan\"},{\"id\":\"feba6ac2-0634-498a-a720-3eba52d2bc0d\",\"title\":\"Administrasi Negara\"}]",
            "jenjang": "[\"Sarjana\"]",
            "ref_status_posisi": {
                "id_status_posisi": 2,
                "nama_status_posisi": "Terverifikasi"
            },
            "program": {
                "id_program": "847c168d-7c13-4fb4-97e6-8169c94ec775",
                "id_sumber_dana": null,
                "id_perusahaan": "8ca7648c-2994-4dc6-ba05-d407208a800b",
                "id_jadwal": "48039861-1251-474e-86af-d904e829093b"
            },
            "perusahaan": {
                "id_perusahaan": "8ca7648c-2994-4dc6-ba05-d407208a800b",
                "id_desa": null,
                "nama_perusahaan": "Balai GTK Provinsi Sulawesi Utara",
                "deskripsi_perusahaan": null,
                "alamat": "Jl. R.W Mongisidi No. 10, Kelurahan Malalayang Satu Timur, Kecamatan Malalayang, Kota Manado, Sulawesi Utara",
                "logo": "https://maganghub.kemnaker.go.id/be/v1/storage/uploads/logo/2025/11/2nwk4OFNRx5A56L1kkzU4xIgmtZqrR7Vcw8jWlgO.png",
                "banner": null,
                "created_at": "2025-11-05 16:05:46",
                "updated_at": "2025-11-05 16:05:46",
                "kode_kabupaten": "7171",
                "nama_kabupaten": "KOTA MANADO",
                "kode_provinsi": "71",
                "nama_provinsi": "SULAWESI UTARA"
            },
            "jadwal": {
                "id_jadwal": "48039861-1251-474e-86af-d904e829093b",
                "angkatan": "2",
                "tanggal_batas_pendaftaran": "2025-10-03 00:00:00",
                "tanggal_mulai": "2025-11-24 00:00:00",
                "tanggal_selesai": "2026-05-23 23:59:59",
                "tahun": "2025",
                "tanggal_rencana_mulai": "2025-10-24 00:00:00",
                "tanggal_rencana_akhir": "2025-11-11 23:59:59",
                "tanggal_seleksi_mulai": "2025-11-12 00:00:00",
                "tanggal_seleksi_akhir": "2025-11-20 23:59:59",
                "tanggal_usulan_mulai": "2025-10-01 00:00:00",
                "tanggal_usulan_akhir": "2025-10-08 00:00:00",
                "tanggal_persetujuan_awal": "2025-10-05 00:00:00",
                "tanggal_persetujuan_akhir": "2025-10-06 00:00:00",
                "tanggal_pendaftaran_awal": "2025-11-06 00:00:00",
                "tanggal_pendaftaran_akhir": "2025-11-14 23:59:59",
                "tanggal_pengumuman_mulai": "2025-11-14 00:00:00",
                "tanggal_pengumuman_akhir": "2025-11-20 23:59:59",
                "tanggal_lulus_awal": "2024-11-01 00:00:00",
                "tanggal_lulus_akhir": "2025-10-31 00:00:00",
                "publish": 1
            },
            "government_agency": {
                "government_agency_name": "Kementerian Pendidikan Dasar dan Menengah"
            },
            "sub_government_agency": {
                "sub_government_agency_name": "Balai GTK Provinsi Sulawesi Utara"
            }
        },
        {
            "id_posisi": "a048978e-1ff9-4683-b4ab-a0384d008697",
            "posisi": "Penunjang Teknik Pengairan",
            "deskripsi_posisi": "Perusahaan Umum Jasa Tirta I\nUnit : Divisi Jasa ASA WS Jratunseluna\nPosisi : Penunjang Teknik Pengairan\nLokasi Penempatan : Kota Semarang\nTugas : Membantu pekerjaan dan pengawasan bidang teknik pengairan",
            "syarat_khusus": null,
            "usia_minimal": null,
            "usia_maksimal": null,
            "revisi": null,
            "id_kondisi_fisik": null,
            "id_program": "e7f0d45b-329a-44ea-9784-84ea77d89cf2",
            "created_at": "2025-11-05 09:16:53",
            "updated_at": "2025-11-05 11:00:30",
            "kode_kbji": null,
            "penempatan": null,
            "id_jenis_kelamin": null,
            "id_status_posisi": 2,
            "jumlah_kuota": 1,
            "jumlah_terdaftar": 1,
            "program_studi": "[{\"id\":\"cf39701a-14ba-4517-a2b8-3bcd2853ff9b\",\"title\":\"Teknik Pengairan\"},{\"id\":\"7191e993-c03d-4d70-8ae6-ac15ceb8d67e\",\"title\":\"Teknik dan Pengelolaan Sumber Daya Air\"}]",
            "jenjang": "[\"Sarjana\"]",
            "ref_status_posisi": {
                "id_status_posisi": 2,
                "nama_status_posisi": "Terverifikasi"
            },
            "program": {
                "id_program": "e7f0d45b-329a-44ea-9784-84ea77d89cf2",
                "id_sumber_dana": null,
                "id_perusahaan": "510f4c61-e52d-444c-8e43-b5418a325fda",
                "id_jadwal": "48039861-1251-474e-86af-d904e829093b"
            },
            "perusahaan": {
                "id_perusahaan": "510f4c61-e52d-444c-8e43-b5418a325fda",
                "id_desa": null,
                "nama_perusahaan": "Perusahaan Umum (Perum) Jasa Tirta I",
                "deskripsi_perusahaan": null,
                "alamat": "Jl. Slamet No.45,",
                "logo": null,
                "banner": null,
                "created_at": "2025-11-05 09:16:53",
                "updated_at": "2025-11-05 11:00:30",
                "kode_kabupaten": "3374",
                "nama_kabupaten": "KOTA SEMARANG",
                "kode_provinsi": "33",
                "nama_provinsi": "JAWA TENGAH"
            },
            "jadwal": {
                "id_jadwal": "48039861-1251-474e-86af-d904e829093b",
                "angkatan": "2",
                "tanggal_batas_pendaftaran": "2025-10-03 00:00:00",
                "tanggal_mulai": "2025-11-24 00:00:00",
                "tanggal_selesai": "2026-05-23 23:59:59",
                "tahun": "2025",
                "tanggal_rencana_mulai": "2025-10-24 00:00:00",
                "tanggal_rencana_akhir": "2025-11-11 23:59:59",
                "tanggal_seleksi_mulai": "2025-11-12 00:00:00",
                "tanggal_seleksi_akhir": "2025-11-20 23:59:59",
                "tanggal_usulan_mulai": "2025-10-01 00:00:00",
                "tanggal_usulan_akhir": "2025-10-08 00:00:00",
                "tanggal_persetujuan_awal": "2025-10-05 00:00:00",
                "tanggal_persetujuan_akhir": "2025-10-06 00:00:00",
                "tanggal_pendaftaran_awal": "2025-11-06 00:00:00",
                "tanggal_pendaftaran_akhir": "2025-11-14 23:59:59",
                "tanggal_pengumuman_mulai": "2025-11-14 00:00:00",
                "tanggal_pengumuman_akhir": "2025-11-20 23:59:59",
                "tanggal_lulus_awal": "2024-11-01 00:00:00",
                "tanggal_lulus_akhir": "2025-10-31 00:00:00",
                "publish": 1
            },
            "government_agency": {
                "government_agency_name": null
            },
            "sub_government_agency": {
                "sub_government_agency_name": null
            }
        },
        {
            "id_posisi": "a04897a3-96e8-4f27-b0ed-91fe1ef27230",
            "posisi": "Tenaga Ahli Lingkungan",
            "deskripsi_posisi": "1. Mampu bekerjasama dengan tim dan klien.\n2. Mengetahui terkait dasar Auto-CAD.\n3. Mampu melakukan penyusunan dokumen perizinan lingkungan seperti Pertek BMAL, Pertek Emisi, Rintek TPS LB3, dll.\n3. Melakukan survey observasi lapangan.",
            "syarat_khusus": null,
            "usia_minimal": null,
            "usia_maksimal": null,
            "revisi": null,
            "id_kondisi_fisik": null,
            "id_program": "c08a84af-78e7-4e27-ad36-ac64bdfce4ea",
            "created_at": "2025-11-05 16:33:17",
            "updated_at": "2025-11-05 16:33:56",
            "kode_kbji": null,
            "penempatan": null,
            "id_jenis_kelamin": null,
            "id_status_posisi": 2,
            "jumlah_kuota": 1,
            "jumlah_terdaftar": 3,
            "program_studi": "[{\"id\":\"03fa0c8f-47f8-4042-951a-a08e48aea3ac\",\"title\":\"Teknik Lingkungan\"},{\"id\":\"0b538bc2-e992-4a5b-bc93-eebddbfe6493\",\"title\":\"Ilmu Lingkungan\"},{\"id\":\"3480b6e7-7599-4333-bb48-2fe3d834162d\",\"title\":\"Teknik Pengolahan Limbah\"},{\"id\":\"f233f939-8568-4d57-aea8-6d731e7b480d\",\"title\":\"Teknik Kimia\"}]",
            "jenjang": "[\"Diploma\",\"Sarjana\"]",
            "ref_status_posisi": {
                "id_status_posisi": 2,
                "nama_status_posisi": "Terverifikasi"
            },
            "program": {
                "id_program": "c08a84af-78e7-4e27-ad36-ac64bdfce4ea",
                "id_sumber_dana": null,
                "id_perusahaan": "dcdeb952-0ef4-4a98-8827-72f1ff3f12c4",
                "id_jadwal": "48039861-1251-474e-86af-d904e829093b"
            },
            "perusahaan": {
                "id_perusahaan": "dcdeb952-0ef4-4a98-8827-72f1ff3f12c4",
                "id_desa": null,
                "nama_perusahaan": "Naztama Bumi Raya",
                "deskripsi_perusahaan": null,
                "alamat": "Jl. Plemahan VII No. 6",
                "logo": "https://wlkp-assets.kemnaker.go.id/companies/57a9226d-014e-40a8-b6eb-c52d2b3062a3/690afbfeb22dd.jpg",
                "banner": "https://wlkp-assets.kemnaker.go.id/companies/57a9226d-014e-40a8-b6eb-c52d2b3062a3/690afc0ad73cc.jpg",
                "created_at": "2025-11-05 16:33:17",
                "updated_at": "2025-11-05 16:33:56",
                "kode_kabupaten": "3578",
                "nama_kabupaten": "KOTA SURABAYA",
                "kode_provinsi": "35",
                "nama_provinsi": "JAWA TIMUR"
            },
            "jadwal": {
                "id_jadwal": "48039861-1251-474e-86af-d904e829093b",
                "angkatan": "2",
                "tanggal_batas_pendaftaran": "2025-10-03 00:00:00",
                "tanggal_mulai": "2025-11-24 00:00:00",
                "tanggal_selesai": "2026-05-23 23:59:59",
                "tahun": "2025",
                "tanggal_rencana_mulai": "2025-10-24 00:00:00",
                "tanggal_rencana_akhir": "2025-11-11 23:59:59",
                "tanggal_seleksi_mulai": "2025-11-12 00:00:00",
                "tanggal_seleksi_akhir": "2025-11-20 23:59:59",
                "tanggal_usulan_mulai": "2025-10-01 00:00:00",
                "tanggal_usulan_akhir": "2025-10-08 00:00:00",
                "tanggal_persetujuan_awal": "2025-10-05 00:00:00",
                "tanggal_persetujuan_akhir": "2025-10-06 00:00:00",
                "tanggal_pendaftaran_awal": "2025-11-06 00:00:00",
                "tanggal_pendaftaran_akhir": "2025-11-14 23:59:59",
                "tanggal_pengumuman_mulai": "2025-11-14 00:00:00",
                "tanggal_pengumuman_akhir": "2025-11-20 23:59:59",
                "tanggal_lulus_awal": "2024-11-01 00:00:00",
                "tanggal_lulus_akhir": "2025-10-31 00:00:00",
                "publish": 1
            },
            "government_agency": {
                "government_agency_name": null
            },
            "sub_government_agency": {
                "sub_government_agency_name": null
            }
        },
        {
            "id_posisi": "a04897aa-92bb-4df4-9d82-edbff5533a34",
            "posisi": "Sales,Shipping & Support Internship",
            "deskripsi_posisi": "Sales (kunimkasi ke customer untuk rencana pengiriman ekspor), Shipping (pembuatan dokumen befor & after sales) & Supporting (Adminstrasi)",
            "syarat_khusus": null,
            "usia_minimal": null,
            "usia_maksimal": null,
            "revisi": null,
            "id_kondisi_fisik": null,
            "id_program": "3d5ae69a-b886-4a8f-9adb-3b6b2b9fc225",
            "created_at": "2025-10-14 09:33:09",
            "updated_at": "2025-10-30 08:06:18",
            "kode_kbji": null,
            "penempatan": null,
            "id_jenis_kelamin": null,
            "id_status_posisi": 2,
            "jumlah_kuota": 1,
            "jumlah_terdaftar": 2,
            "program_studi": "[{\"id\":\"b16054f8-8d35-4fdf-af76-94724b15b73f\",\"title\":\"Manajemen Bisnis\"},{\"id\":\"276643ca-999d-4f19-901c-d5d111941713\",\"title\":\"Administrasi BIsnis\"},{\"id\":\"e12302ac-c8dc-4d0a-90a7-402f6fafd27e\",\"title\":\"Manajemen Pemasaran\\/Marketing\"}]",
            "jenjang": "[\"Sarjana\"]",
            "ref_status_posisi": {
                "id_status_posisi": 2,
                "nama_status_posisi": "Terverifikasi"
            },
            "program": {
                "id_program": "3d5ae69a-b886-4a8f-9adb-3b6b2b9fc225",
                "id_sumber_dana": null,
                "id_perusahaan": "f89ecc16-c282-42fb-a673-7144d7516905",
                "id_jadwal": "48039861-1251-474e-86af-d904e829093b"
            },
            "perusahaan": {
                "id_perusahaan": "f89ecc16-c282-42fb-a673-7144d7516905",
                "id_desa": null,
                "nama_perusahaan": "Great Giant Pineapple",
                "deskripsi_perusahaan": null,
                "alamat": "TERBANGGI BESAR KM. 77",
                "logo": null,
                "banner": null,
                "created_at": "2025-10-14 09:33:09",
                "updated_at": "2025-10-30 08:06:18",
                "kode_kabupaten": "1802",
                "nama_kabupaten": "KAB. LAMPUNG TENGAH",
                "kode_provinsi": "18",
                "nama_provinsi": "LAMPUNG"
            },
            "jadwal": {
                "id_jadwal": "48039861-1251-474e-86af-d904e829093b",
                "angkatan": "2",
                "tanggal_batas_pendaftaran": "2025-10-03 00:00:00",
                "tanggal_mulai": "2025-11-24 00:00:00",
                "tanggal_selesai": "2026-05-23 23:59:59",
                "tahun": "2025",
                "tanggal_rencana_mulai": "2025-10-24 00:00:00",
                "tanggal_rencana_akhir": "2025-11-11 23:59:59",
                "tanggal_seleksi_mulai": "2025-11-12 00:00:00",
                "tanggal_seleksi_akhir": "2025-11-20 23:59:59",
                "tanggal_usulan_mulai": "2025-10-01 00:00:00",
                "tanggal_usulan_akhir": "2025-10-08 00:00:00",
                "tanggal_persetujuan_awal": "2025-10-05 00:00:00",
                "tanggal_persetujuan_akhir": "2025-10-06 00:00:00",
                "tanggal_pendaftaran_awal": "2025-11-06 00:00:00",
                "tanggal_pendaftaran_akhir": "2025-11-14 23:59:59",
                "tanggal_pengumuman_mulai": "2025-11-14 00:00:00",
                "tanggal_pengumuman_akhir": "2025-11-20 23:59:59",
                "tanggal_lulus_awal": "2024-11-01 00:00:00",
                "tanggal_lulus_akhir": "2025-10-31 00:00:00",
                "publish": 1
            },
            "government_agency": {
                "government_agency_name": null
            },
            "sub_government_agency": {
                "sub_government_agency_name": null
            }
        },
        {
            "id_posisi": "a04897ab-d404-4f53-a7df-b25a4b1ed852",
            "posisi": "Statistisi",
            "deskripsi_posisi": "perancangan survei, analisis data menggunakan perangkat lunak statistik, pengembangan model, dan pemublikasian hasil analisis dalam bentuk tabel atau grafik",
            "syarat_khusus": null,
            "usia_minimal": null,
            "usia_maksimal": null,
            "revisi": null,
            "id_kondisi_fisik": null,
            "id_program": "847c168d-7c13-4fb4-97e6-8169c94ec775",
            "created_at": "2025-11-05 16:05:46",
            "updated_at": "2025-11-05 16:05:46",
            "kode_kbji": null,
            "penempatan": null,
            "id_jenis_kelamin": null,
            "id_status_posisi": 2,
            "jumlah_kuota": 1,
            "jumlah_terdaftar": 2,
            "program_studi": "[{\"id\":\"a86f123a-2b95-4d24-b49d-174d3a639d91\",\"title\":\"Statistika\"}]",
            "jenjang": "[\"Sarjana\"]",
            "ref_status_posisi": {
                "id_status_posisi": 2,
                "nama_status_posisi": "Terverifikasi"
            },
            "program": {
                "id_program": "847c168d-7c13-4fb4-97e6-8169c94ec775",
                "id_sumber_dana": null,
                "id_perusahaan": "8ca7648c-2994-4dc6-ba05-d407208a800b",
                "id_jadwal": "48039861-1251-474e-86af-d904e829093b"
            },
            "perusahaan": {
                "id_perusahaan": "8ca7648c-2994-4dc6-ba05-d407208a800b",
                "id_desa": null,
                "nama_perusahaan": "Balai GTK Provinsi Sulawesi Utara",
                "deskripsi_perusahaan": null,
                "alamat": "Jl. R.W Mongisidi No. 10, Kelurahan Malalayang Satu Timur, Kecamatan Malalayang, Kota Manado, Sulawesi Utara",
                "logo": "https://maganghub.kemnaker.go.id/be/v1/storage/uploads/logo/2025/11/2nwk4OFNRx5A56L1kkzU4xIgmtZqrR7Vcw8jWlgO.png",
                "banner": null,
                "created_at": "2025-11-05 16:05:46",
                "updated_at": "2025-11-05 16:05:46",
                "kode_kabupaten": "7171",
                "nama_kabupaten": "KOTA MANADO",
                "kode_provinsi": "71",
                "nama_provinsi": "SULAWESI UTARA"
            },
            "jadwal": {
                "id_jadwal": "48039861-1251-474e-86af-d904e829093b",
                "angkatan": "2",
                "tanggal_batas_pendaftaran": "2025-10-03 00:00:00",
                "tanggal_mulai": "2025-11-24 00:00:00",
                "tanggal_selesai": "2026-05-23 23:59:59",
                "tahun": "2025",
                "tanggal_rencana_mulai": "2025-10-24 00:00:00",
                "tanggal_rencana_akhir": "2025-11-11 23:59:59",
                "tanggal_seleksi_mulai": "2025-11-12 00:00:00",
                "tanggal_seleksi_akhir": "2025-11-20 23:59:59",
                "tanggal_usulan_mulai": "2025-10-01 00:00:00",
                "tanggal_usulan_akhir": "2025-10-08 00:00:00",
                "tanggal_persetujuan_awal": "2025-10-05 00:00:00",
                "tanggal_persetujuan_akhir": "2025-10-06 00:00:00",
                "tanggal_pendaftaran_awal": "2025-11-06 00:00:00",
                "tanggal_pendaftaran_akhir": "2025-11-14 23:59:59",
                "tanggal_pengumuman_mulai": "2025-11-14 00:00:00",
                "tanggal_pengumuman_akhir": "2025-11-20 23:59:59",
                "tanggal_lulus_awal": "2024-11-01 00:00:00",
                "tanggal_lulus_akhir": "2025-10-31 00:00:00",
                "publish": 1
            },
            "government_agency": {
                "government_agency_name": "Kementerian Pendidikan Dasar dan Menengah"
            },
            "sub_government_agency": {
                "sub_government_agency_name": "Balai GTK Provinsi Sulawesi Utara"
            }
        },
        {
            "id_posisi": "a04897b4-a9d7-449f-91cd-87b19c5c8c50",
            "posisi": "Brand & Content Designer",
            "deskripsi_posisi": "Bertanggung jawab dalam pembuatan desain visual dan konten kreatif untuk memperkuat identitas merek perusahaan. Menghasilkan materi promosi, konten media sosial, dan desain pendukung kampanye marketing. Bekerja sama dengan tim marketing dalam merancang strategi branding dan kampanye digital yang efektif.\nMenguasai software desain seperti Adobe Illustrator, Photoshop, Canva, atau aplikasi sejenis untuk menciptakan konten visual yang profesional dan konsisten dengan brand guideline.",
            "syarat_khusus": null,
            "usia_minimal": null,
            "usia_maksimal": null,
            "revisi": null,
            "id_kondisi_fisik": null,
            "id_program": "227ff7b8-32d2-4b95-b285-f3817d08cc1a",
            "created_at": "2025-10-10 14:49:38",
            "updated_at": "2025-10-28 17:19:19",
            "kode_kbji": null,
            "penempatan": null,
            "id_jenis_kelamin": null,
            "id_status_posisi": 2,
            "jumlah_kuota": 1,
            "jumlah_terdaftar": 2,
            "program_studi": "[{\"id\":\"9dfcaa37-a44b-4331-87ab-bd32dc1066cb\",\"title\":\"Desain Komunikasi Visual\"}]",
            "jenjang": "[\"Diploma\",\"Sarjana\"]",
            "ref_status_posisi": {
                "id_status_posisi": 2,
                "nama_status_posisi": "Terverifikasi"
            },
            "program": {
                "id_program": "227ff7b8-32d2-4b95-b285-f3817d08cc1a",
                "id_sumber_dana": null,
                "id_perusahaan": "12d1c51e-986c-4b70-b7fa-d64e87db8636",
                "id_jadwal": "48039861-1251-474e-86af-d904e829093b"
            },
            "perusahaan": {
                "id_perusahaan": "12d1c51e-986c-4b70-b7fa-d64e87db8636",
                "id_desa": null,
                "nama_perusahaan": "PT. Multi Spunindo Jaya, Tbk",
                "deskripsi_perusahaan": "PT Multi Spunindo Jaya adalah produsen nonwoven terkemuka di Indonesia. Kami di sini untuk melakukan lebih dari sekadar memproduksi barang, kami di sini untuk menciptakan solusi yang mengubah hidup Anda setiap hari dan di mana pun.",
                "alamat": "JALAN JABARAN, DESA JABARAN, KECAMATAN BALONGBENDO",
                "logo": "https://wlkp-assets.kemnaker.go.id/companies/12d1c51e-986c-4b70-b7fa-d64e87db8636/615fa17d18291.jpg",
                "banner": "https://wlkp-assets.kemnaker.go.id/companies/12d1c51e-986c-4b70-b7fa-d64e87db8636/615fa6057937d.jpg",
                "created_at": "2025-10-10 14:49:38",
                "updated_at": "2025-10-28 17:19:19",
                "kode_kabupaten": "3515",
                "nama_kabupaten": "KAB. SIDOARJO",
                "kode_provinsi": "35",
                "nama_provinsi": "JAWA TIMUR"
            },
            "jadwal": {
                "id_jadwal": "48039861-1251-474e-86af-d904e829093b",
                "angkatan": "2",
                "tanggal_batas_pendaftaran": "2025-10-03 00:00:00",
                "tanggal_mulai": "2025-11-24 00:00:00",
                "tanggal_selesai": "2026-05-23 23:59:59",
                "tahun": "2025",
                "tanggal_rencana_mulai": "2025-10-24 00:00:00",
                "tanggal_rencana_akhir": "2025-11-11 23:59:59",
                "tanggal_seleksi_mulai": "2025-11-12 00:00:00",
                "tanggal_seleksi_akhir": "2025-11-20 23:59:59",
                "tanggal_usulan_mulai": "2025-10-01 00:00:00",
                "tanggal_usulan_akhir": "2025-10-08 00:00:00",
                "tanggal_persetujuan_awal": "2025-10-05 00:00:00",
                "tanggal_persetujuan_akhir": "2025-10-06 00:00:00",
                "tanggal_pendaftaran_awal": "2025-11-06 00:00:00",
                "tanggal_pendaftaran_akhir": "2025-11-14 23:59:59",
                "tanggal_pengumuman_mulai": "2025-11-14 00:00:00",
                "tanggal_pengumuman_akhir": "2025-11-20 23:59:59",
                "tanggal_lulus_awal": "2024-11-01 00:00:00",
                "tanggal_lulus_akhir": "2025-10-31 00:00:00",
                "publish": 1
            },
            "government_agency": {
                "government_agency_name": null
            },
            "sub_government_agency": {
                "sub_government_agency_name": null
            }
        },
        {
            "id_posisi": "a04897b9-1976-4ad0-bda7-4cbb25002a44",
            "posisi": "Pranata Humas (Desain Grafis dan Multimedia), Sekretariat KPI, Jakarta",
            "deskripsi_posisi": "1. Membuat desain visual untuk media cetak seperti brosur, poster, spanduk, dan laporan tahunan. \n2.\tMerancang identitas visual instansi seperti logo dan simbol (desain corporate).\n3.\tMengembangkan desain untuk publikasi dan materi promosi. \n4.\tMembuat dan menyunting video untuk publikasi, edukasi, atau kampanye.\n5.\tMengembangkan desain untuk website instansi dan aplikasi mobile. \n6.\tMembuat animasi dan grafis bergerak untuk konten digital. \n7.\tMendesain grafis dan video untuk media sosial, termasuk materi kampanye literasi digital. \n8. Membuat infografis dan visualisasi data untuk berbagai platform. \n9. Mengelola dan mengarsipkan aset desain.\n10. Menyusun laporan bulanan atau akhir terkait hasil kerja dan efektivitas desain.",
            "syarat_khusus": null,
            "usia_minimal": null,
            "usia_maksimal": null,
            "revisi": null,
            "id_kondisi_fisik": null,
            "id_program": "490100d9-125d-4c95-93b3-2adaf9ed7ca9",
            "created_at": "2025-11-05 15:05:10",
            "updated_at": "2025-11-05 15:05:10",
            "kode_kbji": null,
            "penempatan": null,
            "id_jenis_kelamin": null,
            "id_status_posisi": 2,
            "jumlah_kuota": 1,
            "jumlah_terdaftar": 2,
            "program_studi": "[{\"id\":\"9dfcaa37-a44b-4331-87ab-bd32dc1066cb\",\"title\":\"Desain Komunikasi Visual\"},{\"id\":\"e2843b4a-1c93-44b9-bafd-c667c91efd9c\",\"title\":\"Desain Media\"},{\"id\":\"011b8525-c183-4a3c-b05e-a9642a5d1e52\",\"title\":\"Teknik Multimedia Digital\"},{\"id\":\"70e608e6-2966-4560-a767-867fcd634628\",\"title\":\"Animasi\"},{\"id\":\"e90b7fe8-f4a5-4a1c-85f8-e929004b29e1\",\"title\":\"Desain Grafis\"}]",
            "jenjang": "[\"Sarjana\",\"Diploma\"]",
            "ref_status_posisi": {
                "id_status_posisi": 2,
                "nama_status_posisi": "Terverifikasi"
            },
            "program": {
                "id_program": "490100d9-125d-4c95-93b3-2adaf9ed7ca9",
                "id_sumber_dana": null,
                "id_perusahaan": "a4798d05-184b-4f58-889e-a233143a4e27",
                "id_jadwal": "48039861-1251-474e-86af-d904e829093b"
            },
            "perusahaan": {
                "id_perusahaan": "a4798d05-184b-4f58-889e-a233143a4e27",
                "id_desa": null,
                "nama_perusahaan": "Sekretariat Komisi Penyiaran Indonesia",
                "deskripsi_perusahaan": null,
                "alamat": "Jl. Ir. H. Juanda No.36, RT.7/RW.2, Kb. Klp., Kecamatan Gambir, Kota Jakarta Pusat, Daerah Khusus Ibukota Jakarta",
                "logo": "https://maganghub.kemnaker.go.id/be/v1/storage/uploads/logo/2025/11/N7wZjz1noctNPmTpn6EbWkpbxFSSn8hMff6yM24s.png",
                "banner": null,
                "created_at": "2025-11-05 15:05:10",
                "updated_at": "2025-11-05 15:05:10",
                "kode_kabupaten": "3171",
                "nama_kabupaten": "KOTA ADM. JAKARTA PUSAT",
                "kode_provinsi": "31",
                "nama_provinsi": "DKI JAKARTA"
            },
            "jadwal": {
                "id_jadwal": "48039861-1251-474e-86af-d904e829093b",
                "angkatan": "2",
                "tanggal_batas_pendaftaran": "2025-10-03 00:00:00",
                "tanggal_mulai": "2025-11-24 00:00:00",
                "tanggal_selesai": "2026-05-23 23:59:59",
                "tahun": "2025",
                "tanggal_rencana_mulai": "2025-10-24 00:00:00",
                "tanggal_rencana_akhir": "2025-11-11 23:59:59",
                "tanggal_seleksi_mulai": "2025-11-12 00:00:00",
                "tanggal_seleksi_akhir": "2025-11-20 23:59:59",
                "tanggal_usulan_mulai": "2025-10-01 00:00:00",
                "tanggal_usulan_akhir": "2025-10-08 00:00:00",
                "tanggal_persetujuan_awal": "2025-10-05 00:00:00",
                "tanggal_persetujuan_akhir": "2025-10-06 00:00:00",
                "tanggal_pendaftaran_awal": "2025-11-06 00:00:00",
                "tanggal_pendaftaran_akhir": "2025-11-14 23:59:59",
                "tanggal_pengumuman_mulai": "2025-11-14 00:00:00",
                "tanggal_pengumuman_akhir": "2025-11-20 23:59:59",
                "tanggal_lulus_awal": "2024-11-01 00:00:00",
                "tanggal_lulus_akhir": "2025-10-31 00:00:00",
                "publish": 1
            },
            "government_agency": {
                "government_agency_name": "Kementerian Komunikasi dan Digital"
            },
            "sub_government_agency": {
                "sub_government_agency_name": "Sekretariat Komisi Penyiaran Indonesia"
            }
        },
        {
            "id_posisi": "a04897c4-8aca-4ad5-8c9a-d08a8dad5c26",
            "posisi": "Staf Pendukung Analis Kebijakan Bidang Ketenagakerjaan dan Transmigrasi",
            "deskripsi_posisi": "1. Mendukung pelaksanaan Rapat Koordinasi Teknis Pembangunan Daerah\n2. Membantu melakukan penyusunan Bahan presentasi terkait kebijakan UMP dan kebijakan\nketenagakerjaan\n3. Membantu proses Notulensi Rapat",
            "syarat_khusus": null,
            "usia_minimal": null,
            "usia_maksimal": null,
            "revisi": null,
            "id_kondisi_fisik": null,
            "id_program": "46c8bad9-ba9d-4ea7-be31-218cb8f3087c",
            "created_at": "2025-11-05 16:17:10",
            "updated_at": "2025-11-05 16:17:10",
            "kode_kbji": null,
            "penempatan": null,
            "id_jenis_kelamin": null,
            "id_status_posisi": 2,
            "jumlah_kuota": 1,
            "jumlah_terdaftar": 1,
            "program_studi": "[{\"id\":\"2e8c9cee-6fae-45b2-bb89-14fdcdb0ef9f\",\"title\":\"Pembangunan Wilayah\"},{\"id\":\"7551b4b0-9160-465c-9065-be559c153ce7\",\"title\":\"Administrasi Publik\"},{\"id\":\"62c7cc14-9834-43f6-8f09-3d00e94c6671\",\"title\":\"Manajemen dan Kebijakan Publik\"},{\"id\":\"feba6ac2-0634-498a-a720-3eba52d2bc0d\",\"title\":\"Administrasi Negara\"},{\"id\":\"588f15f5-fb46-459f-a554-703fac78179f\",\"title\":\"Manajemen Industri\"}]",
            "jenjang": "[\"Sarjana\",\"Diploma\"]",
            "ref_status_posisi": {
                "id_status_posisi": 2,
                "nama_status_posisi": "Terverifikasi"
            },
            "program": {
                "id_program": "46c8bad9-ba9d-4ea7-be31-218cb8f3087c",
                "id_sumber_dana": null,
                "id_perusahaan": "e18a4308-90bd-49ce-89e5-56e588930402",
                "id_jadwal": "48039861-1251-474e-86af-d904e829093b"
            },
            "perusahaan": {
                "id_perusahaan": "e18a4308-90bd-49ce-89e5-56e588930402",
                "id_desa": null,
                "nama_perusahaan": "Direktorat Jenderal Bina Pembangunan Daerah",
                "deskripsi_perusahaan": null,
                "alamat": "Jalan Makam Pahlawan Nomor 20 Kalibata",
                "logo": "https://maganghub.kemnaker.go.id/be/v1/storage/uploads/logo/2025/11/2WowcjFBm7Ddil5sszBe5DMDMxggYXZsMeDqk4js.png",
                "banner": null,
                "created_at": "2025-11-05 16:17:10",
                "updated_at": "2025-11-05 16:17:10",
                "kode_kabupaten": "3174",
                "nama_kabupaten": "KOTA ADM. JAKARTA SELATAN",
                "kode_provinsi": "31",
                "nama_provinsi": "DKI JAKARTA"
            },
            "jadwal": {
                "id_jadwal": "48039861-1251-474e-86af-d904e829093b",
                "angkatan": "2",
                "tanggal_batas_pendaftaran": "2025-10-03 00:00:00",
                "tanggal_mulai": "2025-11-24 00:00:00",
                "tanggal_selesai": "2026-05-23 23:59:59",
                "tahun": "2025",
                "tanggal_rencana_mulai": "2025-10-24 00:00:00",
                "tanggal_rencana_akhir": "2025-11-11 23:59:59",
                "tanggal_seleksi_mulai": "2025-11-12 00:00:00",
                "tanggal_seleksi_akhir": "2025-11-20 23:59:59",
                "tanggal_usulan_mulai": "2025-10-01 00:00:00",
                "tanggal_usulan_akhir": "2025-10-08 00:00:00",
                "tanggal_persetujuan_awal": "2025-10-05 00:00:00",
                "tanggal_persetujuan_akhir": "2025-10-06 00:00:00",
                "tanggal_pendaftaran_awal": "2025-11-06 00:00:00",
                "tanggal_pendaftaran_akhir": "2025-11-14 23:59:59",
                "tanggal_pengumuman_mulai": "2025-11-14 00:00:00",
                "tanggal_pengumuman_akhir": "2025-11-20 23:59:59",
                "tanggal_lulus_awal": "2024-11-01 00:00:00",
                "tanggal_lulus_akhir": "2025-10-31 00:00:00",
                "publish": 1
            },
            "government_agency": {
                "government_agency_name": "Kementerian Dalam Negeri"
            },
            "sub_government_agency": {
                "sub_government_agency_name": "Direktorat Jenderal Bina Pembangunan Daerah"
            }
        }
    ],
    "meta": {
        "pagination": {
            "current_page": 661,
            "first_page_url": null,
            "from": 13201,
            "last_page": 789,
            "last_page_url": null,
            "links": null,
            "next_page_url": null,
            "path": null,
            "per_page": 20,
            "prev_page_url": null,
            "to": 13220,
            "total": 15761
        }
    }
}